{"version": 0.6, "generator": "Overpass API 0.7.62.5 1bd436f1", "osm3s": {"timestamp_osm_base": "2025-05-16T02:41:12Z", "copyright": "The data included in this document is from www.openstreetmap.org. The data is made available under ODbL."}, "elements": [{"type": "node", "id": 414684881, "lat": 37.5230555, "lon": 127.1071754, "tags": {"name:en": "Jamsil High School Front", "name:ko": "\uc7a0\uc2e4\uace0\uad50\uc55e", "name:ko-Latn": "Jamsilgogyoap", "ncat": "\uad50\ucc28\ub85c\ubc0f\uc9c0\uba85", "source": "mp2osm"}}, {"type": "node", "id": 414684896, "lat": 37.5247449, "lon": 127.1110557}, {"type": "node", "id": 436808709, "lat": 37.5144726, "lon": 127.1209097}, {"type": "node", "id": 436811817, "lat": 37.5270386, "lon": 127.1214694, "tags": {"highway": "traffic_signals", "traffic_signals": "signal"}}, {"type": "node", "id": 436812039, "lat": 37.5252346, "lon": 127.1255235}, {"type": "node", "id": 436812044, "lat": 37.5259999, "lon": 127.1238125, "tags": {"junction": "yes", "name": "\uc62c\ub9bc\ud53d\uacf5\uc6d0\ubd811\ubb38", "name:en": "Olympic Park North Gate 1", "name:ko": "\uc62c\ub9bc\ud53d\uacf5\uc6d0\ubd811\ubb38"}}, {"type": "node", "id": 436812061, "lat": 37.5255241, "lon": 127.1201776}, {"type": "node", "id": 436812062, "lat": 37.5253967, "lon": 127.1196299}, {"type": "node", "id": 436812065, "lat": 37.5253602, "lon": 127.1184512}, {"type": "node", "id": 436812069, "lat": 37.5254332, "lon": 127.1180747}, {"type": "node", "id": 436812075, "lat": 37.5266256, "lon": 127.1151647}, {"type": "node", "id": 436812078, "lat": 37.5267808, "lon": 127.1147516}, {"type": "node", "id": 436812084, "lat": 37.5269127, "lon": 127.1143868}, {"type": "node", "id": 436812087, "lat": 37.5269872, "lon": 127.1140489}, {"type": "node", "id": 436812093, "lat": 37.5271578, "lon": 127.1129663}, {"type": "node", "id": 436812124, "lat": 37.5272389, "lon": 127.1124262}, {"type": "node", "id": 436812128, "lat": 37.5273943, "lon": 127.11177}, {"type": "node", "id": 436812131, "lat": 37.5275368, "lon": 127.1113336}, {"type": "node", "id": 436812135, "lat": 37.5277245, "lon": 127.110887}, {"type": "node", "id": 436812139, "lat": 37.5281656, "lon": 127.1100678}, {"type": "node", "id": 436812154, "lat": 37.5264801, "lon": 127.1227966}, {"type": "node", "id": 436825247, "lat": 37.529736, "lon": 127.1232927}, {"type": "node", "id": 436855499, "lat": 37.52893, "lon": 127.12503}, {"type": "node", "id": 436855500, "lat": 37.52947, "lon": 127.12385}, {"type": "node", "id": 436859341, "lat": 37.5191676, "lon": 127.1080684}, {"type": "node", "id": 436859347, "lat": 37.5201358, "lon": 127.114296}, {"type": "node", "id": 436860185, "lat": 37.5246884, "lon": 127.1156147}, {"type": "node", "id": 436860186, "lat": 37.5246984, "lon": 127.1163293}, {"type": "node", "id": 436860187, "lat": 37.5248071, "lon": 127.1165497}, {"type": "node", "id": 436866941, "lat": 37.5158683, "lon": 127.1169556}, {"type": "node", "id": 436869430, "lat": 37.5229416, "lon": 127.1042969}, {"type": "node", "id": 436869431, "lat": 37.5230045, "lon": 127.1043458}, {"type": "node", "id": 436869432, "lat": 37.5230485, "lon": 127.1044057}, {"type": "node", "id": 436869433, "lat": 37.5230651, "lon": 127.1044739}, {"type": "node", "id": 436869440, "lat": 37.52308, "lon": 127.11385}, {"type": "node", "id": 436869441, "lat": 37.5230758, "lon": 127.1147217}, {"type": "node", "id": 436869447, "lat": 37.5225543, "lon": 127.1153279}, {"type": "node", "id": 436869448, "lat": 37.5223428, "lon": 127.1156718}, {"type": "node", "id": 436869449, "lat": 37.5161687, "lon": 127.1087288, "tags": {"name:en": "Jamsiljinju Apt. Front", "name:ko": "\uc7a0\uc2e4\uc9c4\uc8fc\uc544\ud30c\ud2b8\uc55e", "name:ko-Latn": "Jamsiljinjuapateuap", "ncat": "\uad50\ucc28\ub85c\ubc0f\uc9c0\uba85", "source": "mp2osm"}}, {"type": "node", "id": 436877179, "lat": 37.5279603, "lon": 127.1191217, "tags": {"highway": "traffic_signals", "junction": "yes", "name": "\ud48d\ub0a9\uc0ac\uac70\ub9ac", "name:ko": "\ud48d\ub0a9\uc0ac\uac70\ub9ac", "traffic_signals": "signal"}}, {"type": "node", "id": 436877180, "lat": 37.5288, "lon": 127.11722}, {"type": "node", "id": 436877181, "lat": 37.5293398, "lon": 127.115888}, {"type": "node", "id": 436877182, "lat": 37.5298052, "lon": 127.1147396}, {"type": "node", "id": 436877186, "lat": 37.530887, "lon": 127.1124253}, {"type": "node", "id": 436877187, "lat": 37.53122, "lon": 127.11171}, {"type": "node", "id": 436877188, "lat": 37.53157, "lon": 127.111}, {"type": "node", "id": 436878386, "lat": 37.5316724, "lon": 127.1106986}, {"type": "node", "id": 436878399, "lat": 37.5296956, "lon": 127.1201882}, {"type": "node", "id": 436878439, "lat": 37.5270469, "lon": 127.1134405}, {"type": "node", "id": 797051279, "lat": 37.5278533, "lon": 127.1104068}, {"type": "node", "id": 797051476, "lat": 37.5273666, "lon": 127.111517}, {"type": "node", "id": 797051479, "lat": 37.5271385, "lon": 127.1124732}, {"type": "node", "id": 797051482, "lat": 37.5271058, "lon": 127.1127967}, {"type": "node", "id": 797051486, "lat": 37.5270446, "lon": 127.1135446}, {"type": "node", "id": 797051489, "lat": 37.5270533, "lon": 127.1136573}, {"type": "node", "id": 797051631, "lat": 37.5269165, "lon": 127.1148377}, {"type": "node", "id": 797051634, "lat": 37.5272123, "lon": 127.1136874}, {"type": "node", "id": 797051635, "lat": 37.5273968, "lon": 127.1124428}, {"type": "node", "id": 797051636, "lat": 37.5275756, "lon": 127.1117937}, {"type": "node", "id": 797051637, "lat": 37.5278068, "lon": 127.1111267}, {"type": "node", "id": 797051638, "lat": 37.5280538, "lon": 127.1105859}, {"type": "node", "id": 797051639, "lat": 37.5283278, "lon": 127.1100929}, {"type": "node", "id": 797051665, "lat": 37.5275575, "lon": 127.1122997}, {"type": "node", "id": 797051666, "lat": 37.5277306, "lon": 127.1117141}, {"type": "node", "id": 797051668, "lat": 37.5284562, "lon": 127.1100544}, {"type": "node", "id": 797051669, "lat": 37.5286549, "lon": 127.1098431}, {"type": "node", "id": 797051670, "lat": 37.5288648, "lon": 127.1097126}, {"type": "node", "id": 797051850, "lat": 37.5259321, "lon": 127.1216949}, {"type": "node", "id": 797051851, "lat": 37.5260059, "lon": 127.1222666}, {"type": "node", "id": 797051852, "lat": 37.5259774, "lon": 127.1228811}, {"type": "node", "id": 797051853, "lat": 37.5258505, "lon": 127.1234124}, {"type": "node", "id": 797051854, "lat": 37.5256786, "lon": 127.1239239}, {"type": "node", "id": 797051857, "lat": 37.521756, "lon": 127.1329337}, {"type": "node", "id": 797051901, "lat": 37.5262091, "lon": 127.1229608}, {"type": "node", "id": 797051904, "lat": 37.5261539, "lon": 127.1216763}, {"type": "node", "id": 797051907, "lat": 37.5255427, "lon": 127.1195602}, {"type": "node", "id": 797051908, "lat": 37.5254947, "lon": 127.1191574}, {"type": "node", "id": 797051909, "lat": 37.5254774, "lon": 127.1186724}, {"type": "node", "id": 797051910, "lat": 37.5255693, "lon": 127.1181283}, {"type": "node", "id": 798555855, "lat": 37.5235806, "lon": 127.1286153}, {"type": "node", "id": 798555856, "lat": 37.5238061, "lon": 127.1287279}, {"type": "node", "id": 845893207, "lat": 37.5172148, "lon": 127.1140206}, {"type": "node", "id": 845893619, "lat": 37.5148153, "lon": 127.1207066}, {"type": "node", "id": 845894226, "lat": 37.5164653, "lon": 127.1152703}, {"type": "node", "id": 845894231, "lat": 37.5166308, "lon": 127.1156267}, {"type": "node", "id": 845975955, "lat": 37.5102801, "lon": 127.1122021, "tags": {"junction": "yes", "name": "\ubc29\uc774\uc0ac\uac70\ub9ac", "name:en": "Bangi Crossroad", "name:ko": "\ubc29\uc774\uc0ac\uac70\ub9ac", "name:ko-Latn": "Bangisageori", "ncat": "\uad50\ucc28\ub85c\ubc0f\uc9c0\uba85", "source": "mp2osm"}}, {"type": "node", "id": 845975970, "lat": 37.5164731, "lon": 127.1160485}, {"type": "node", "id": 845976007, "lat": 37.5218873, "lon": 127.132532}, {"type": "node", "id": 999136499, "lat": 37.5264114, "lon": 127.1221064}, {"type": "node", "id": 999136618, "lat": 37.5266013, "lon": 127.1224933}, {"type": "node", "id": 999136624, "lat": 37.5262836, "lon": 127.1219627}, {"type": "node", "id": 999136632, "lat": 37.5255478, "lon": 127.1176179}, {"type": "node", "id": 1809560158, "lat": 37.5157205, "lon": 127.1119601}, {"type": "node", "id": 1809560160, "lat": 37.5157574, "lon": 127.1156387}, {"type": "node", "id": 1809560165, "lat": 37.5169248, "lon": 127.1123392}, {"type": "node", "id": 1809560173, "lat": 37.5161375, "lon": 127.1086469}, {"type": "node", "id": 1809564266, "lat": 37.5160076, "lon": 127.110671}, {"type": "node", "id": 1809564267, "lat": 37.516728, "lon": 127.1103605}, {"type": "node", "id": 1809564270, "lat": 37.5115734, "lon": 127.1105303}, {"type": "node", "id": 1809564277, "lat": 37.5163259, "lon": 127.1140486}, {"type": "node", "id": 1809564281, "lat": 37.5148283, "lon": 127.1142629}, {"type": "node", "id": 1809564285, "lat": 37.5168215, "lon": 127.1126382}, {"type": "node", "id": 1809564292, "lat": 37.5164552, "lon": 127.1124193}, {"type": "node", "id": 1809564294, "lat": 37.5159877, "lon": 127.1149821}, {"type": "node", "id": 1809564300, "lat": 37.5166574, "lon": 127.1131104}, {"type": "node", "id": 1809564304, "lat": 37.5169844, "lon": 127.1138924}, {"type": "node", "id": 1809564307, "lat": 37.5150074, "lon": 127.113804}, {"type": "node", "id": 1809564309, "lat": 37.5151901, "lon": 127.1133486}, {"type": "node", "id": 1809564318, "lat": 37.5165284, "lon": 127.112209}, {"type": "node", "id": 1809564320, "lat": 37.5142798, "lon": 127.1122234}, {"type": "node", "id": 1809564321, "lat": 37.5164872, "lon": 127.1136067}, {"type": "node", "id": 1809564328, "lat": 37.5127166, "lon": 127.1112365}, {"type": "node", "id": 1809564330, "lat": 37.5161569, "lon": 127.1145168}, {"type": "node", "id": 1809564334, "lat": 37.5153694, "lon": 127.1128811}, {"type": "node", "id": 1809564341, "lat": 37.5161041, "lon": 127.1121917}, {"type": "node", "id": 1809578785, "lat": 37.5141646, "lon": 127.1200584}, {"type": "node", "id": 1809578792, "lat": 37.51435, "lon": 127.1154646}, {"type": "node", "id": 1809578809, "lat": 37.5120325, "lon": 127.116642}, {"type": "node", "id": 1809578813, "lat": 37.5141839, "lon": 127.1158868}, {"type": "node", "id": 1809578816, "lat": 37.5155459, "lon": 127.1162109}, {"type": "node", "id": 1809584162, "lat": 37.5153896, "lon": 127.1166331}, {"type": "node", "id": 1809584188, "lat": 37.5148139, "lon": 127.1199868}, {"type": "node", "id": 1809584190, "lat": 37.5130278, "lon": 127.115168}, {"type": "node", "id": 1809584198, "lat": 37.5143059, "lon": 127.1196519}, {"type": "node", "id": 1809584201, "lat": 37.5144643, "lon": 127.1192138}, {"type": "node", "id": 1809584213, "lat": 37.5146131, "lon": 127.1188023}, {"type": "node", "id": 1809613950, "lat": 37.515088, "lon": 127.1174929}, {"type": "node", "id": 1809613951, "lat": 37.5147843, "lon": 127.1183502}, {"type": "node", "id": 1809613952, "lat": 37.5127198, "lon": 127.1170685}, {"type": "node", "id": 1809613953, "lat": 37.5133797, "lon": 127.1153879}, {"type": "node", "id": 1809613956, "lat": 37.5152397, "lon": 127.1170668}, {"type": "node", "id": 1809613958, "lat": 37.513738, "lon": 127.1156095}, {"type": "node", "id": 1809613959, "lat": 37.5152705, "lon": 127.1186567}, {"type": "node", "id": 1809613960, "lat": 37.5149325, "lon": 127.1179236}, {"type": "node", "id": 1809613961, "lat": 37.5140213, "lon": 127.1163079}, {"type": "node", "id": 1809613964, "lat": 37.513522, "lon": 127.1175658}, {"type": "node", "id": 1809613966, "lat": 37.5130762, "lon": 127.1172898}, {"type": "node", "id": 2346858828, "lat": 37.5174935, "lon": 127.1127369, "tags": {"bicycle": "yes"}}, {"type": "node", "id": 2477228800, "lat": 37.5230708, "lon": 127.1113267}, {"type": "node", "id": 2477228825, "lat": 37.5200917, "lon": 127.1139765, "tags": {"crossing": "traffic_signals", "highway": "crossing"}}, {"type": "node", "id": 2477229063, "lat": 37.5198, "lon": 127.1121079}, {"type": "node", "id": 2477230545, "lat": 37.5232813, "lon": 127.1162478}, {"type": "node", "id": 2477230552, "lat": 37.5282109, "lon": 127.1105613}, {"type": "node", "id": 2477231265, "lat": 37.5246669, "lon": 127.1171172}, {"type": "node", "id": 2477231277, "lat": 37.5275265, "lon": 127.1203301}, {"type": "node", "id": 2477232307, "lat": 37.5233273, "lon": 127.1175871}, {"type": "node", "id": 2477232318, "lat": 37.5233302, "lon": 127.1178659, "tags": {"amenity": "shelter"}}, {"type": "node", "id": 2477237066, "lat": 37.5140496, "lon": 127.122821}, {"type": "node", "id": 2477237874, "lat": 37.5250298, "lon": 127.1253817}, {"type": "node", "id": 2477237876, "lat": 37.5285935, "lon": 127.1224931}, {"type": "node", "id": 2477239843, "lat": 37.523883, "lon": 127.1279243}, {"type": "node", "id": 2477239844, "lat": 37.5240952, "lon": 127.1280411, "tags": {"junction": "yes", "name": "\uc62c\ub9bc\ud53d\uacf5\uc6d0\ubd812\ubb38", "name:ko": "\uc62c\ub9bc\ud53d\uacf5\uc6d0\ubd812\ubb38"}}, {"type": "node", "id": 2477247449, "lat": 37.5156339, "lon": 127.1184028}, {"type": "node", "id": 2477248313, "lat": 37.5186422, "lon": 127.1134113}, {"type": "node", "id": 2912275815, "lat": 37.5123649, "lon": 127.1168451}, {"type": "node", "id": 2918341058, "lat": 37.5233174, "lon": 127.1166213}, {"type": "node", "id": 2918341059, "lat": 37.5233557, "lon": 127.1164817}, {"type": "node", "id": 2918341060, "lat": 37.5233549, "lon": 127.1162956}, {"type": "node", "id": 3583849859, "lat": 37.5275045, "lon": 127.1111322}, {"type": "node", "id": 3851762045, "lat": 37.5273392, "lon": 127.113725}, {"type": "node", "id": 3851762046, "lat": 37.5279503, "lon": 127.1146123}, {"type": "node", "id": 3851762047, "lat": 37.5284762, "lon": 127.1154156}, {"type": "node", "id": 3851762048, "lat": 37.5292992, "lon": 127.1159843}, {"type": "node", "id": 3851762049, "lat": 37.5265615, "lon": 127.1156613}, {"type": "node", "id": 3851762050, "lat": 37.527272, "lon": 127.1161564}, {"type": "node", "id": 3851762051, "lat": 37.52641, "lon": 127.1181368}, {"type": "node", "id": 3851762052, "lat": 37.5289399, "lon": 127.1157314}, {"type": "node", "id": 3851762053, "lat": 37.5284023, "lon": 127.1169432}, {"type": "node", "id": 3851762054, "lat": 37.5275576, "lon": 127.1188594}, {"type": "node", "id": 3851762055, "lat": 37.528067, "lon": 127.1177011}, {"type": "node", "id": 3851762056, "lat": 37.5275984, "lon": 127.1174132}, {"type": "node", "id": 3851762257, "lat": 37.5285821, "lon": 127.1165379}, {"type": "node", "id": 3851762258, "lat": 37.5274467, "lon": 127.1157588}, {"type": "node", "id": 3851762259, "lat": 37.5267359, "lon": 127.1152568}, {"type": "node", "id": 3851762260, "lat": 37.5287575, "lon": 127.1161424}, {"type": "node", "id": 3851762261, "lat": 37.5276249, "lon": 127.115353}, {"type": "node", "id": 3851762262, "lat": 37.5278078, "lon": 127.1149368}, {"type": "node", "id": 3851762264, "lat": 37.52706, "lon": 127.1144592}, {"type": "node", "id": 3851762265, "lat": 37.527853, "lon": 127.114471}, {"type": "node", "id": 3851762266, "lat": 37.5277431, "lon": 127.1145058}, {"type": "node", "id": 3851762267, "lat": 37.5276876, "lon": 127.1144918}, {"type": "node", "id": 3851762268, "lat": 37.5271444, "lon": 127.114124}, {"type": "node", "id": 3851762269, "lat": 37.5298775, "lon": 127.1145554}, {"type": "node", "id": 3851762278, "lat": 37.531013, "lon": 127.1121516}, {"type": "node", "id": 3851762284, "lat": 37.5305797, "lon": 127.1130443}, {"type": "node", "id": 3853477683, "lat": 37.5297106, "lon": 127.1149633}, {"type": "node", "id": 3853477694, "lat": 37.5301608, "lon": 127.1138907}, {"type": "node", "id": 3853477696, "lat": 37.5306052, "lon": 127.1129887}, {"type": "node", "id": 3853477745, "lat": 37.5285983, "lon": 127.1176627}, {"type": "node", "id": 3853477746, "lat": 37.5303286, "lon": 127.1187287}, {"type": "node", "id": 3853477747, "lat": 37.5303656, "lon": 127.1188641}, {"type": "node", "id": 3853477748, "lat": 37.5309482, "lon": 127.1192614}, {"type": "node", "id": 3853477749, "lat": 37.531726, "lon": 127.1198403}, {"type": "node", "id": 3853477751, "lat": 37.5313072, "lon": 127.1195285}, {"type": "node", "id": 3853477752, "lat": 37.528934, "lon": 127.1169056}, {"type": "node", "id": 3853477754, "lat": 37.53011, "lon": 127.118594}, {"type": "node", "id": 3853477757, "lat": 37.5290087, "lon": 127.1179155}, {"type": "node", "id": 3853477774, "lat": 37.531133, "lon": 127.1119058}, {"type": "node", "id": 3853477876, "lat": 37.5302489, "lon": 127.1137197}, {"type": "node", "id": 3853477878, "lat": 37.5303562, "lon": 127.1134955}, {"type": "node", "id": 3853477879, "lat": 37.5304837, "lon": 127.1132442}, {"type": "node", "id": 3856535907, "lat": 37.522726, "lon": 127.1311558}, {"type": "node", "id": 3856535938, "lat": 37.5221986, "lon": 127.1323719}, {"type": "node", "id": 3856536062, "lat": 37.5242133, "lon": 127.1277758}, {"type": "node", "id": 3856536065, "lat": 37.5283433, "lon": 127.123071}, {"type": "node", "id": 3856536067, "lat": 37.5290344, "lon": 127.1235489}, {"type": "node", "id": 3856536068, "lat": 37.5273116, "lon": 127.1254541}, {"type": "node", "id": 3856536070, "lat": 37.5283834, "lon": 127.1262045}, {"type": "node", "id": 3856536071, "lat": 37.5278255, "lon": 127.1242671}, {"type": "node", "id": 3856536073, "lat": 37.529303, "lon": 127.12095}, {"type": "node", "id": 3856536076, "lat": 37.5294818, "lon": 127.1205611}, {"type": "node", "id": 3856536094, "lat": 37.5276056, "lon": 127.120131}, {"type": "node", "id": 3856536095, "lat": 37.5292364, "lon": 127.1210947}, {"type": "node", "id": 3856536096, "lat": 37.5292898, "lon": 127.1229805}, {"type": "node", "id": 3856536113, "lat": 37.5290636, "lon": 127.1214708}, {"type": "node", "id": 3856536115, "lat": 37.5288468, "lon": 127.1219421}, {"type": "node", "id": 3856536120, "lat": 37.5281738, "lon": 127.1234626}, {"type": "node", "id": 3856536121, "lat": 37.5288535, "lon": 127.1239429}, {"type": "node", "id": 3856536122, "lat": 37.5280021, "lon": 127.1238591}, {"type": "node", "id": 3856536123, "lat": 37.5286816, "lon": 127.1243171}, {"type": "node", "id": 3856536124, "lat": 37.5276449, "lon": 127.1246843}, {"type": "node", "id": 3856536125, "lat": 37.5283019, "lon": 127.1251439}, {"type": "node", "id": 3856536126, "lat": 37.5274828, "lon": 127.1250585}, {"type": "node", "id": 3856536127, "lat": 37.5281411, "lon": 127.1254941}, {"type": "node", "id": 3856536128, "lat": 37.5271392, "lon": 127.1258522}, {"type": "node", "id": 3856536129, "lat": 37.527776, "lon": 127.1262891}, {"type": "node", "id": 3856536130, "lat": 37.5269687, "lon": 127.126246}, {"type": "node", "id": 3856536131, "lat": 37.5275917, "lon": 127.1266904}, {"type": "node", "id": 3856536261, "lat": 37.5288388, "lon": 127.1208635}, {"type": "node", "id": 3856536263, "lat": 37.5264293, "lon": 127.1263785}, {"type": "node", "id": 3856536264, "lat": 37.5255887, "lon": 127.1282415}, {"type": "node", "id": 3856536267, "lat": 37.5281444, "lon": 127.1204596}, {"type": "node", "id": 3856536269, "lat": 37.5257497, "lon": 127.1258921}, {"type": "node", "id": 3856536270, "lat": 37.5249167, "lon": 127.1277744}, {"type": "node", "id": 3856536271, "lat": 37.5267316, "lon": 127.1236344}, {"type": "node", "id": 3856536272, "lat": 37.5274229, "lon": 127.1241274}, {"type": "node", "id": 3856536273, "lat": 37.5277771, "lon": 127.1243788}, {"type": "node", "id": 3856536274, "lat": 37.5285039, "lon": 127.1206687}, {"type": "node", "id": 3856536276, "lat": 37.5270733, "lon": 127.1238781}, {"type": "node", "id": 3856536277, "lat": 37.5265539, "lon": 127.1240429}, {"type": "node", "id": 3856536278, "lat": 37.5272505, "lon": 127.124518}, {"type": "node", "id": 3856536279, "lat": 37.5269122, "lon": 127.1242873}, {"type": "node", "id": 3856536280, "lat": 37.5260842, "lon": 127.1261315}, {"type": "node", "id": 3856536281, "lat": 37.5252542, "lon": 127.128009}, {"type": "node", "id": 3958847216, "lat": 37.5263545, "lon": 127.1220774}, {"type": "node", "id": 3958847217, "lat": 37.5269193, "lon": 127.1169668}, {"type": "node", "id": 3969132982, "lat": 37.5219052, "lon": 127.1330617}, {"type": "node", "id": 4187713491, "lat": 37.511932, "lon": 127.1132188}, {"type": "node", "id": 4187713492, "lat": 37.5145825, "lon": 127.1148706}, {"type": "node", "id": 4187713493, "lat": 37.5139473, "lon": 127.1120054}, {"type": "node", "id": 4187713499, "lat": 37.5163141, "lon": 127.1105381}, {"type": "node", "id": 4187713500, "lat": 37.5155457, "lon": 127.1124162}, {"type": "node", "id": 4190893753, "lat": 37.524698, "lon": 127.1147907}, {"type": "node", "id": 4191904191, "lat": 37.5267973, "lon": 127.1266419}, {"type": "node", "id": 4191922820, "lat": 37.528251, "lon": 127.1222508}, {"type": "node", "id": 4191922821, "lat": 37.5279091, "lon": 127.122009}, {"type": "node", "id": 4191922822, "lat": 37.5275492, "lon": 127.1217543}, {"type": "node", "id": 4191922824, "lat": 37.5284875, "lon": 127.1247399}, {"type": "node", "id": 4191922825, "lat": 37.527952, "lon": 127.1259059}, {"type": "node", "id": 4254083553, "lat": 37.5234212, "lon": 127.1163382}, {"type": "node", "id": 4254083554, "lat": 37.5243769, "lon": 127.1169424}, {"type": "node", "id": 4636654762, "lat": 37.5206025, "lon": 127.1140763}, {"type": "node", "id": 4636654766, "lat": 37.5203803, "lon": 127.1127849}, {"type": "node", "id": 4636654767, "lat": 37.5206939, "lon": 127.1146285}, {"type": "node", "id": 4636654768, "lat": 37.5206675, "lon": 127.112707}, {"type": "node", "id": 4636654769, "lat": 37.5199253, "lon": 127.1129084}, {"type": "node", "id": 4636670593, "lat": 37.5205942, "lon": 127.1140281}, {"type": "node", "id": 4636670595, "lat": 37.5205342, "lon": 127.1136794}, {"type": "node", "id": 4659574359, "lat": 37.5230727, "lon": 127.1118433}, {"type": "node", "id": 4659574362, "lat": 37.5230528, "lon": 127.1070473}, {"type": "node", "id": 4664955066, "lat": 37.5230721, "lon": 127.1116926}, {"type": "node", "id": 4664955068, "lat": 37.5230696, "lon": 127.1109879}, {"type": "node", "id": 4664955069, "lat": 37.5230657, "lon": 127.109938}, {"type": "node", "id": 4664955071, "lat": 37.5230644, "lon": 127.1095926}, {"type": "node", "id": 4664955074, "lat": 37.5230623, "lon": 127.1090254}, {"type": "node", "id": 4664955075, "lat": 37.5230616, "lon": 127.108821}, {"type": "node", "id": 4664955077, "lat": 37.5230595, "lon": 127.1082679}, {"type": "node", "id": 4664955078, "lat": 37.5230602, "lon": 127.1084618}, {"type": "node", "id": 4679959424, "lat": 37.5167637, "lon": 127.1144404}, {"type": "node", "id": 4679959425, "lat": 37.5159083, "lon": 127.1168425}, {"type": "node", "id": 4680041425, "lat": 37.5200132, "lon": 127.1142374}, {"type": "node", "id": 4680721607, "lat": 37.5253543, "lon": 127.1191813}, {"type": "node", "id": 4680721611, "lat": 37.5241476, "lon": 127.127269}, {"type": "node", "id": 4680721612, "lat": 37.5239942, "lon": 127.1276131}, {"type": "node", "id": 4680721613, "lat": 37.5225803, "lon": 127.1314856}, {"type": "node", "id": 4680721615, "lat": 37.5224049, "lon": 127.131335}, {"type": "node", "id": 4680822159, "lat": 37.5247145, "lon": 127.1171436}, {"type": "node", "id": 4681593288, "lat": 37.5222813, "lon": 127.1156375}, {"type": "node", "id": 4937969970, "lat": 37.5247111, "lon": 127.1129724}, {"type": "node", "id": 5159098835, "lat": 37.523068, "lon": 127.104789}, {"type": "node", "id": 5260056212, "lat": 37.5253321, "lon": 127.1177174, "tags": {"highway": "crossing"}}, {"type": "node", "id": 5260056684, "lat": 37.5277663, "lon": 127.1202357}, {"type": "node", "id": 5273519247, "lat": 37.5276035, "lon": 127.1141088}, {"type": "node", "id": 5273854549, "lat": 37.5258764, "lon": 127.117809}, {"type": "node", "id": 5273854568, "lat": 37.5249149, "lon": 127.1112308}, {"type": "node", "id": 5273854569, "lat": 37.5247428, "lon": 127.1115297}, {"type": "node", "id": 5304584193, "lat": 37.5230688, "lon": 127.1045627}, {"type": "node", "id": 5304584194, "lat": 37.5228661, "lon": 127.1042781}, {"type": "node", "id": 5804563290, "lat": 37.529094, "lon": 127.119849}, {"type": "node", "id": 5896568485, "lat": 37.5228757, "lon": 127.1151521}, {"type": "node", "id": 5896568486, "lat": 37.5229985, "lon": 127.1149692}, {"type": "node", "id": 5896568487, "lat": 37.5227156, "lon": 127.1152403}, {"type": "node", "id": 5896568488, "lat": 37.5223144, "lon": 127.1154247}, {"type": "node", "id": 6344468478, "lat": 37.516451, "lon": 127.1135565}, {"type": "node", "id": 6344476921, "lat": 37.5154294, "lon": 127.1129227}, {"type": "node", "id": 6344476922, "lat": 37.514328, "lon": 127.1122356}, {"type": "node", "id": 6344485732, "lat": 37.5142487, "lon": 127.1122137}, {"type": "node", "id": 6344485733, "lat": 37.5139872, "lon": 127.112054}, {"type": "node", "id": 6346331454, "lat": 37.5159823, "lon": 127.1150232}, {"type": "node", "id": 6348622162, "lat": 37.5149554, "lon": 127.117895}, {"type": "node", "id": 6348622163, "lat": 37.5150862, "lon": 127.117529}, {"type": "node", "id": 6348622164, "lat": 37.5152633, "lon": 127.1170365}, {"type": "node", "id": 6348622165, "lat": 37.5153895, "lon": 127.1166789}, {"type": "node", "id": 6348622166, "lat": 37.5154106, "lon": 127.1166725}, {"type": "node", "id": 6458482380, "lat": 37.5230682, "lon": 127.1047226}, {"type": "node", "id": 6546731616, "lat": 37.5282134, "lon": 127.119317, "tags": {"crossing": "traffic_signals", "crossing:island": "no", "highway": "crossing", "tactile_paving": "yes"}}, {"type": "node", "id": 6546731627, "lat": 37.527915, "lon": 127.1193872}, {"type": "node", "id": 6546731628, "lat": 37.5280675, "lon": 127.1188719}, {"type": "node", "id": 6546731629, "lat": 37.5277618, "lon": 127.118978}, {"type": "node", "id": 6546731630, "lat": 37.5269802, "lon": 127.1216255}, {"type": "node", "id": 6546731631, "lat": 37.5256641, "lon": 127.1172924}, {"type": "node", "id": 6546731632, "lat": 37.5258114, "lon": 127.1174015}, {"type": "node", "id": 6546731633, "lat": 37.5256205, "lon": 127.117924}, {"type": "node", "id": 6546731634, "lat": 37.5254839, "lon": 127.1178274}, {"type": "node", "id": 6546731635, "lat": 37.525204, "lon": 127.1172726}, {"type": "node", "id": 6546731636, "lat": 37.5253947, "lon": 127.1175331}, {"type": "node", "id": 6546731640, "lat": 37.5238918, "lon": 127.1285384}, {"type": "node", "id": 6546731641, "lat": 37.5236818, "lon": 127.1283945}, {"type": "node", "id": 6960603044, "lat": 37.5199312, "lon": 127.1141759, "tags": {"crossing": "traffic_signals", "highway": "crossing"}}, {"type": "node", "id": 6960603045, "lat": 37.5202582, "lon": 127.1143719, "tags": {"crossing": "traffic_signals", "highway": "crossing"}}, {"type": "node", "id": 7609153889, "lat": 37.5253481, "lon": 127.1256042}, {"type": "node", "id": 7609153901, "lat": 37.5251048, "lon": 127.1252133}, {"type": "node", "id": 7609153902, "lat": 37.5253066, "lon": 127.1253551}, {"type": "node", "id": 7986032166, "lat": 37.5247503, "lon": 127.1083903}, {"type": "node", "id": 8043994877, "lat": 37.5247494, "lon": 127.1088729}, {"type": "node", "id": 8046442205, "lat": 37.5285267, "lon": 127.117825}, {"type": "node", "id": 8116819797, "lat": 37.5162564, "lon": 127.108992}, {"type": "node", "id": 8116819807, "lat": 37.5200861, "lon": 127.1128648}, {"type": "node", "id": 8116864617, "lat": 37.5203409, "lon": 127.1127956}, {"type": "node", "id": 8116864626, "lat": 37.5191809, "lon": 127.1081534, "tags": {"crossing": "marked", "highway": "crossing"}}, {"type": "node", "id": 8116864631, "lat": 37.519814, "lon": 127.1121971, "tags": {"crossing": "marked", "highway": "crossing"}}, {"type": "node", "id": 8116864632, "lat": 37.5197852, "lon": 127.1120132, "tags": {"crossing": "marked", "highway": "crossing"}}, {"type": "node", "id": 8116864633, "lat": 37.5199786, "lon": 127.1128939, "tags": {"highway": "crossing"}}, {"type": "node", "id": 8116864636, "lat": 37.5194122, "lon": 127.1096307, "tags": {"crossing": "marked", "highway": "crossing"}}, {"type": "node", "id": 8357174039, "lat": 37.5245278, "lon": 127.1170348}, {"type": "node", "id": 8357174040, "lat": 37.5252151, "lon": 127.1171539}, {"type": "node", "id": 8431981076, "lat": 37.5250661, "lon": 127.1169011}, {"type": "node", "id": 8431981077, "lat": 37.5251754, "lon": 127.1170731}, {"type": "node", "id": 8432257673, "lat": 37.5143079, "lon": 127.1221142}, {"type": "node", "id": 8436639415, "lat": 37.5174185, "lon": 127.1124052}, {"type": "node", "id": 8436639416, "lat": 37.5184026, "lon": 127.1132792}, {"type": "node", "id": 8436639417, "lat": 37.5183341, "lon": 127.1131532}, {"type": "node", "id": 8436639418, "lat": 37.5180346, "lon": 127.1129233}, {"type": "node", "id": 8436639419, "lat": 37.5177981, "lon": 127.1127091}, {"type": "node", "id": 8436639420, "lat": 37.517701, "lon": 127.1126215}, {"type": "node", "id": 8436639421, "lat": 37.5176379, "lon": 127.112533}, {"type": "node", "id": 8436639422, "lat": 37.5175755, "lon": 127.112406}, {"type": "node", "id": 8436639423, "lat": 37.5174523, "lon": 127.1121557}, {"type": "node", "id": 8436639424, "lat": 37.5171933, "lon": 127.1115911}, {"type": "node", "id": 8437329856, "lat": 37.5173883, "lon": 127.1130627}, {"type": "node", "id": 8442852754, "lat": 37.5251616, "lon": 127.117404}, {"type": "node", "id": 8442852756, "lat": 37.5247447, "lon": 127.1099771}, {"type": "node", "id": 8442852772, "lat": 37.5247479, "lon": 127.1080406}, {"type": "node", "id": 8550523621, "lat": 37.5253615, "lon": 127.1178125}, {"type": "node", "id": 8550523622, "lat": 37.52532, "lon": 127.1176784}, {"type": "node", "id": 8550523623, "lat": 37.5252647, "lon": 127.1175376}, {"type": "node", "id": 8550523624, "lat": 37.5252211, "lon": 127.117437}, {"type": "node", "id": 8693812050, "lat": 37.5272566, "lon": 127.113263}, {"type": "node", "id": 8946638422, "lat": 37.5206586, "lon": 127.1143754, "tags": {"crossing": "marked", "highway": "crossing"}}, {"type": "node", "id": 8969922149, "lat": 37.5253716, "lon": 127.117849, "tags": {"highway": "crossing"}}, {"type": "node", "id": 8969922169, "lat": 37.5174279, "lon": 127.112936, "tags": {"highway": "crossing"}}, {"type": "node", "id": 8969922170, "lat": 37.5175567, "lon": 127.1127821}, {"type": "node", "id": 8969922171, "lat": 37.5176964, "lon": 127.1128563, "tags": {"highway": "crossing"}}, {"type": "node", "id": 8969922173, "lat": 37.5174566, "lon": 127.112573, "tags": {"highway": "crossing"}}, {"type": "node", "id": 8969922174, "lat": 37.5177821, "lon": 127.1126947, "tags": {"crossing": "marked", "highway": "crossing", "tactile_paving": "yes"}}, {"type": "node", "id": 8969922176, "lat": 37.527205, "lon": 127.1215336, "tags": {"highway": "crossing"}}, {"type": "node", "id": 8997539840, "lat": 37.5300186, "lon": 127.1142243}, {"type": "node", "id": 9079503583, "lat": 37.5161023, "lon": 127.1158381}, {"type": "node", "id": 9079503585, "lat": 37.5162411, "lon": 127.1159167}, {"type": "node", "id": 9533959333, "lat": 37.5271106, "lon": 127.1142987}, {"type": "node", "id": 9533959334, "lat": 37.5279927, "lon": 127.1110083}, {"type": "node", "id": 9533959335, "lat": 37.5273068, "lon": 127.1128998}, {"type": "node", "id": 9533959336, "lat": 37.5268242, "lon": 127.1130505}, {"type": "node", "id": 9533959337, "lat": 37.5268946, "lon": 127.1131456}, {"type": "node", "id": 9533959338, "lat": 37.5269927, "lon": 127.1132715}, {"type": "node", "id": 9533959339, "lat": 37.5280025, "lon": 127.1103537}, {"type": "node", "id": 9533959342, "lat": 37.5272391, "lon": 127.111972}, {"type": "node", "id": 9533959343, "lat": 37.5270413, "lon": 127.112973}, {"type": "node", "id": 9533959344, "lat": 37.5269875, "lon": 127.1130315}, {"type": "node", "id": 9533959345, "lat": 37.5269255, "lon": 127.1130428}, {"type": "node", "id": 9664699415, "lat": 37.5276685, "lon": 127.1235709}, {"type": "node", "id": 9664699423, "lat": 37.5274607, "lon": 127.1240417}, {"type": "node", "id": 9664699424, "lat": 37.5275791, "lon": 127.1237735}, {"type": "node", "id": 9664699426, "lat": 37.5272341, "lon": 127.1235184}, {"type": "node", "id": 9664699430, "lat": 37.5279873, "lon": 127.1238933}, {"type": "node", "id": 10009448544, "lat": 37.5224105, "lon": 127.1154008, "tags": {"crossing": "marked", "highway": "crossing"}}, {"type": "node", "id": 10009448548, "lat": 37.5233464, "lon": 127.1165157, "tags": {"highway": "crossing"}}, {"type": "node", "id": 10777963309, "lat": 37.525683, "lon": 127.1176896, "tags": {"junction": "yes", "name": "\uc62c\ub9bc\ud53d\ub300\uad50\ub0a8\ub2e8", "name:en": "Olympicdaegyo South End", "name:ko": "\uc62c\ub9bc\ud53d\ub300\uad50\ub0a8\ub2e8"}}, {"type": "node", "id": 10777963310, "lat": 37.5256652, "lon": 127.1177575}, {"type": "node", "id": 10923903160, "lat": 37.5276614, "lon": 127.1107518}, {"type": "node", "id": 10923903234, "lat": 37.5287439, "lon": 127.1097832}, {"type": "node", "id": 10923903235, "lat": 37.5285598, "lon": 127.1099313}, {"type": "node", "id": 11177272192, "lat": 37.5165126, "lon": 127.1151388}, {"type": "node", "id": 11177272193, "lat": 37.5165207, "lon": 127.1153733}, {"type": "node", "id": 11177272194, "lat": 37.516568, "lon": 127.1154812}, {"type": "node", "id": 11177272195, "lat": 37.5166209, "lon": 127.1155039}, {"type": "node", "id": 11177272196, "lat": 37.5166881, "lon": 127.1154691}, {"type": "node", "id": 11177272197, "lat": 37.5174058, "lon": 127.113452}, {"type": "node", "id": 11177272198, "lat": 37.5174833, "lon": 127.1132951}, {"type": "node", "id": 11177272199, "lat": 37.5176655, "lon": 127.1131405}, {"type": "node", "id": 11177272200, "lat": 37.5177712, "lon": 127.1131047}, {"type": "node", "id": 11177272201, "lat": 37.5178579, "lon": 127.1131047}, {"type": "node", "id": 11177272202, "lat": 37.5181329, "lon": 127.1131314}, {"type": "node", "id": 11177272203, "lat": 37.5204346, "lon": 127.1144758}, {"type": "node", "id": 11177272204, "lat": 37.5202997, "lon": 127.1142741, "tags": {"crossing": "traffic_signals", "highway": "crossing"}}, {"type": "node", "id": 11177272205, "lat": 37.5202026, "lon": 127.1141348}, {"type": "node", "id": 11177272206, "lat": 37.5200482, "lon": 127.1136976}, {"type": "node", "id": 11177272207, "lat": 37.5200342, "lon": 127.1138703}, {"type": "node", "id": 11177272208, "lat": 37.5199545, "lon": 127.1139679, "tags": {"crossing": "traffic_signals", "highway": "crossing"}}, {"type": "node", "id": 11177272209, "lat": 37.5198783, "lon": 127.1140147}, {"type": "node", "id": 11177272210, "lat": 37.5196862, "lon": 127.1140332}, {"type": "node", "id": 11177272211, "lat": 37.5220961, "lon": 127.1155198}, {"type": "node", "id": 11177272212, "lat": 37.5226551, "lon": 127.1158634}, {"type": "node", "id": 11177272213, "lat": 37.5225686, "lon": 127.1157262}, {"type": "node", "id": 11177272214, "lat": 37.5225488, "lon": 127.1155867}, {"type": "node", "id": 11177272215, "lat": 37.5225557, "lon": 127.115493, "tags": {"crossing": "uncontrolled", "crossing:markings": "yes", "highway": "crossing"}}, {"type": "node", "id": 11177272216, "lat": 37.5225919, "lon": 127.1154179}, {"type": "node", "id": 11177272217, "lat": 37.5228877, "lon": 127.115224}, {"type": "node", "id": 11177272218, "lat": 37.5229669, "lon": 127.1151506}, {"type": "node", "id": 11177272219, "lat": 37.5230309, "lon": 127.1150493}, {"type": "node", "id": 11177272220, "lat": 37.5230729, "lon": 127.1149583}, {"type": "node", "id": 11177272224, "lat": 37.5176896, "lon": 127.1131323}, {"type": "node", "id": 11177272228, "lat": 37.5172504, "lon": 127.1123023}, {"type": "node", "id": 11177272229, "lat": 37.5172903, "lon": 127.1125244}, {"type": "node", "id": 11177272230, "lat": 37.5172894, "lon": 127.1126895}, {"type": "node", "id": 11177272231, "lat": 37.5172628, "lon": 127.1128077}, {"type": "node", "id": 11177272232, "lat": 37.5171755, "lon": 127.1131826}, {"type": "node", "id": 11177272233, "lat": 37.5170898, "lon": 127.1135945}, {"type": "node", "id": 11229084224, "lat": 37.5236858, "lon": 127.1290212}, {"type": "node", "id": 11229097838, "lat": 37.5244691, "lon": 127.1274625}, {"type": "node", "id": 11229097839, "lat": 37.5243177, "lon": 127.1275699}, {"type": "node", "id": 11229097840, "lat": 37.5245471, "lon": 127.1273137}, {"type": "node", "id": 11229097841, "lat": 37.5250025, "lon": 127.1262739}, {"type": "node", "id": 11229097842, "lat": 37.5251305, "lon": 127.1257569}, {"type": "node", "id": 11229097850, "lat": 37.5253439, "lon": 127.1252678}, {"type": "node", "id": 11229097851, "lat": 37.5255899, "lon": 127.1249283}, {"type": "node", "id": 11229097852, "lat": 37.526716, "lon": 127.1224054}, {"type": "node", "id": 11229097853, "lat": 37.5268908, "lon": 127.1218361}, {"type": "node", "id": 11229097854, "lat": 37.5278036, "lon": 127.1196889}, {"type": "node", "id": 11229097855, "lat": 37.5279178, "lon": 127.119604}, {"type": "node", "id": 11229097856, "lat": 37.5280252, "lon": 127.1194869}, {"type": "node", "id": 11229097857, "lat": 37.5281117, "lon": 127.1193997}, {"type": "node", "id": 11229097858, "lat": 37.5272397, "lon": 127.1210509}, {"type": "node", "id": 11229097859, "lat": 37.5274262, "lon": 127.1207324}, {"type": "node", "id": 11229097860, "lat": 37.5275661, "lon": 127.1204808}, {"type": "node", "id": 11229097861, "lat": 37.5277982, "lon": 127.1199067}, {"type": "node", "id": 11229097862, "lat": 37.5277009, "lon": 127.1201746}, {"type": "node", "id": 11229097863, "lat": 37.5278062, "lon": 127.1193177}, {"type": "node", "id": 11229097864, "lat": 37.5273989, "lon": 127.120247}, {"type": "node", "id": 11229097865, "lat": 37.5269528, "lon": 127.1212297}, {"type": "node", "id": 11229097866, "lat": 37.5265607, "lon": 127.1220905}, {"type": "node", "id": 11229097867, "lat": 37.5264831, "lon": 127.1221082}, {"type": "node", "id": 11229097868, "lat": 37.5262246, "lon": 127.1222631}, {"type": "node", "id": 11229097869, "lat": 37.5262384, "lon": 127.1225474}, {"type": "node", "id": 11229097870, "lat": 37.5265068, "lon": 127.1221566}, {"type": "node", "id": 11229097871, "lat": 37.5262272, "lon": 127.1223171}, {"type": "node", "id": 11229097872, "lat": 37.526112, "lon": 127.1223716}, {"type": "node", "id": 11229097873, "lat": 37.5259983, "lon": 127.1224145}, {"type": "node", "id": 11229097874, "lat": 37.5265344, "lon": 127.1228123}, {"type": "node", "id": 11229097876, "lat": 37.5268237, "lon": 127.1215134}, {"type": "node", "id": 11229097879, "lat": 37.5273852, "lon": 127.1206813}, {"type": "node", "id": 11229097880, "lat": 37.5269374, "lon": 127.1213521}, {"type": "node", "id": 11229097881, "lat": 37.5269731, "lon": 127.1214241}, {"type": "node", "id": 12129019916, "lat": 37.5247489, "lon": 127.1089912}, {"type": "node", "id": 12129019920, "lat": 37.5264772, "lon": 127.1179824}, {"type": "node", "id": 12129019937, "lat": 37.5249648, "lon": 127.1112783}, {"type": "node", "id": 12129019942, "lat": 37.5268013, "lon": 127.1130287}, {"type": "node", "id": 12129019943, "lat": 37.5259392, "lon": 127.1122072}, {"type": "node", "id": 12129019948, "lat": 37.5276328, "lon": 127.1186884}, {"type": "node", "id": 12129019949, "lat": 37.5268089, "lon": 127.1153084}, {"type": "node", "id": 12129019954, "lat": 37.5269943, "lon": 127.1148943}, {"type": "node", "id": 12129019960, "lat": 37.5266359, "lon": 127.1157131}, {"type": "node", "id": 12129019965, "lat": 37.5271502, "lon": 127.1145168}, {"type": "node", "id": 12129019976, "lat": 37.5272438, "lon": 127.1141913}, {"type": "way", "id": 37398845, "nodes": [999136618, 11229097853, 6546731630, 436811817, 11229097858, 11229097879], "tags": {"highway": "secondary", "lanes": "3", "name": "\uac15\ub3d9\ub300\ub85c", "name:en": "Gangdong-daero", "name:ko": "\uac15\ub3d9\ub300\ub85c", "name:ko-Latn": "Gangdong-daero", "oneway": "yes", "smoothness": "excellent", "surface": "asphalt"}}, {"type": "way", "id": 37398852, "nodes": [436812139, 9533959339, 436812135, 436812131, 436812128, 436812124, 436812093, 797051489], "tags": {"bicycle": "designated", "cycleway:right": "opposite_track", "highway": "secondary", "layer": "1", "name": "\uac15\ub3d9\ub300\ub85c", "name:en": "Gangdong-daero", "name:ko": "\uac15\ub3d9\ub300\ub85c", "name:ko-Latn": "Gangdong-daero", "oneway": "yes", "ref": "60", "surface": "asphalt"}}, {"type": "way", "id": 37399464, "nodes": [436811817, 8969922176, 4191922822, 4191922821, 4191922820, 2477237876, 3856536096, 436825247], "tags": {"highway": "tertiary", "name": "\uc131\ub0b4\ub85c6\uae38", "name:en": "Seongnae-ro 6-gil", "name:ko": "\uc131\ub0b4\ub85c6\uae38", "ncat": "\uad11\uc5ed\uc2dc\ub3c4\ub85c", "review": "no", "source": "NTIC", "surface": "asphalt"}}, {"type": "way", "id": 37401713, "nodes": [2477229063, 8116864632, 8116864636, 8116864626, 436859341], "tags": {"highway": "tertiary", "name": "\uc62c\ub9bc\ud53d\ub85c35\uae38", "name:en": "Olympic-ro 35-gil", "name:ko": "\uc62c\ub9bc\ud53d\ub85c35\uae38", "ncat": "\uad11\uc5ed\uc2dc\ub3c4\ub85c", "review": "no", "source": "NTIC"}}, {"type": "way", "id": 37403022, "nodes": [436877179, 6546731628, 8046442205, 3853477745, 436877180, 3853477752, 3851762048, 436877181, 3853477683, 436877182, 3851762269, 8997539840, 3853477694, 3853477876, 3853477878, 3853477879, 3851762284, 3853477696, 436877186, 3851762278, 3853477774, 436877187, 436877188, 436878386], "tags": {"cycleway:both": "no", "highway": "tertiary", "lanes": "2", "name": "\ud1a0\uc131\ub85c", "name:en": "Toseong-ro", "name:ko": "\ud1a0\uc131\ub85c", "smoothness": "excellent", "surface": "asphalt"}}, {"type": "way", "id": 37403091, "nodes": [8442852754, 6546731635, 8357174040, 8431981077, 8431981076, 436860187, 436860186, 436860185, 4190893753, 4937969970, 5273854569, 414684896, 8442852756, 12129019916, 8043994877, 7986032166, 8442852772], "tags": {"highway": "tertiary", "lanes": "2", "name": "\uc62c\ub9bc\ud53d\ub85c43\uae38", "name:en": "Olympic-ro 43-gil", "name:ko": "\uc62c\ub9bc\ud53d\ub85c43\uae38", "surface": "asphalt"}}, {"type": "way", "id": 37403099, "nodes": [414684896, 5273854568, 12129019937, 12129019943, 12129019942, 9533959336], "tags": {"highway": "tertiary", "name": "\uac15\ub3d9\ub300\ub85c2\uae38", "name:en": "Gangdong-daero 2-gil", "name:ko": "\uac15\ub3d9\ub300\ub85c2\uae38", "surface": "asphalt"}}, {"type": "way", "id": 59097446, "nodes": [436877179, 6546731629, 3851762054, 3851762051, 5273854549, 10777963309], "tags": {"cycleway:both": "no", "highway": "primary", "lanes": "8", "name": "\uc62c\ub9bc\ud53d\ub85c", "name:en": "Olympic-ro", "name:ja": "\u30aa\u30ea\u30f3\u30d4\u30c3\u30af \u8def", "name:ko": "\uc62c\ub9bc\ud53d\ub85c", "name:ko-Latn": "Ollimpingno", "ref": "90", "surface": "asphalt"}}, {"type": "way", "id": 65115499, "nodes": [8693812050, 797051665, 797051666, 9533959334, 2477230552, 797051668, 10923903235, 797051669, 10923903234, 797051670], "tags": {"highway": "trunk_link", "oneway": "yes"}}, {"type": "way", "id": 70986632, "nodes": [9079503585, 4679959425, 436866941, 1809613959, 1809584188, 436808709], "tags": {"highway": "secondary", "name": "\uc704\ub840\uc131\ub300\ub85c", "name:en": "Wiryeseong-daero", "name:ko": "\uc704\ub840\uc131\ub300\ub85c", "ncat": "\uad11\uc5ed\uc2dc\ub3c4\ub85c", "official_ref": "4237", "oneway": "yes", "review": "no", "source": "NTIC"}}, {"type": "way", "id": 70986638, "nodes": [8437329856, 8969922169, 2346858828], "tags": {"highway": "secondary", "name": "\uc704\ub840\uc131\ub300\ub85c", "name:en": "Wiryeseong-daero", "name:ko": "\uc704\ub840\uc131\ub300\ub85c", "ncat": "\uad11\uc5ed\uc2dc\ub3c4\ub85c", "official_ref": "4237", "review": "no", "source": "NTIC", "surface": "asphalt"}}, {"type": "way", "id": 70986639, "nodes": [8437329856, 11177272233, 1809564304, 4679959424], "tags": {"highway": "secondary", "name": "\uc704\ub840\uc131\ub300\ub85c", "name:en": "Wiryeseong-daero", "name:ko": "\uc704\ub840\uc131\ub300\ub85c", "ncat": "\uad11\uc5ed\uc2dc\ub3c4\ub85c", "official_ref": "4237", "oneway": "yes", "review": "no", "source": "NTIC", "surface": "asphalt"}}, {"type": "way", "id": 70986692, "nodes": [2477237066, 8432257673, 845893619, 2477247449, 845975970], "tags": {"highway": "secondary", "name": "\uc704\ub840\uc131\ub300\ub85c", "name:en": "Wiryeseong-daero", "name:ko": "\uc704\ub840\uc131\ub300\ub85c", "ncat": "\uad11\uc5ed\uc2dc\ub3c4\ub85c", "official_ref": "4237", "oneway": "yes", "review": "no", "source": "NTIC"}}, {"type": "way", "id": 70986698, "nodes": [845975970, 845894231, 11177272196, 845893207, 8437329856], "tags": {"highway": "secondary", "name": "\uc704\ub840\uc131\ub300\ub85c", "name:en": "Wiryeseong-daero", "name:ko": "\uc704\ub840\uc131\ub300\ub85c", "ncat": "\uad11\uc5ed\uc2dc\ub3c4\ub85c", "official_ref": "4237", "oneway": "yes", "review": "no", "source": "NTIC", "surface": "asphalt"}}, {"type": "way", "id": 70998383, "nodes": [845975970, 9079503585, 9079503583, 1809560160, 4187713492, 4187713491, 845975955], "tags": {"highway": "tertiary", "name": "\ubc31\uc81c\uace0\ubd84\ub85c", "name:en": "Baekjegobun-ro", "name:ko": "\ubc31\uc81c\uace0\ubd84\ub85c", "name:ko-Latn": "Baekjegobunno", "surface": "asphalt"}}, {"type": "way", "id": 86099090, "nodes": [11229097866, 11229097867, 999136499, 3958847216, 999136624, 797051904], "tags": {"highway": "secondary_link", "oneway": "yes", "surface": "asphalt"}}, {"type": "way", "id": 169794656, "nodes": [1809560160, 6346331454, 1809564294, 1809564330, 1809564277, 1809564321, 1809564300, 1809564285, 1809560165], "tags": {"highway": "residential", "name": "\ubc31\uc81c\uace0\ubd84\ub85c51\uae38", "name:en": "Baekjegobun-ro 51-gil", "name:ko": "\ubc31\uc81c\uace0\ubd84\ub85c51\uae38"}}, {"type": "way", "id": 169795484, "nodes": [1809564294, 1809564281], "tags": {"highway": "residential", "name": "\uc624\uae08\ub85c11\uae38", "name:en": "Ogeum-ro 11-gil", "name:ko": "\uc624\uae08\ub85c11\uae38", "surface": "asphalt"}}, {"type": "way", "id": 169795486, "nodes": [1809564285, 1809564292, 1809564341, 1809560158], "tags": {"highway": "residential", "name": "\uc624\uae08\ub85c11\uae38", "name:en": "Ogeum-ro 11-gil", "name:ko": "\uc624\uae08\ub85c11\uae38", "surface": "asphalt"}}, {"type": "way", "id": 169795487, "nodes": [1809564266, 1809564318, 1809564292], "tags": {"highway": "residential", "name": "\uc62c\ub9bc\ud53d\ub85c34\uae38", "name:en": "Olympic-ro 34-gil", "name:ko": "\uc62c\ub9bc\ud53d\ub85c34\uae38", "surface": "asphalt"}}, {"type": "way", "id": 169795488, "nodes": [1809564330, 1809564307], "tags": {"highway": "residential", "name": "\uc624\uae08\ub85c11\uae38", "name:en": "Ogeum-ro 11-gil", "name:ko": "\uc624\uae08\ub85c11\uae38", "surface": "asphalt"}}, {"type": "way", "id": 169795497, "nodes": [1809564277, 1809564309], "tags": {"highway": "residential", "name": "\uc624\uae08\ub85c11\uae38", "name:en": "Ogeum-ro 11-gil", "name:ko": "\uc624\uae08\ub85c11\uae38", "surface": "asphalt"}}, {"type": "way", "id": 169795501, "nodes": [1809564270, 1809564328, 4187713493, 6344485733, 6344485732, 1809564320, 6344476922, 1809564334, 6344476921, 6344468478, 1809564321, 1809564304], "tags": {"highway": "residential", "name": "\uc704\ub840\uc131\ub300\ub85c2\uae38", "name:en": "Wiryeseong-daero 2-gil", "name:ko": "\uc704\ub840\uc131\ub300\ub85c2\uae38"}}, {"type": "way", "id": 169800396, "nodes": [1809578809, 2912275815, 1809613952, 1809613966, 1809613964, 1809613951, 1809613959], "tags": {"highway": "residential", "name": "\uc704\ub840\uc131\ub300\ub85c6\uae38", "name:en": "Wiryeseong-daero 6-gil", "name:ko": "\uc704\ub840\uc131\ub300\ub85c6\uae38"}}, {"type": "way", "id": 169800401, "nodes": [1809613956, 1809613961], "tags": {"highway": "residential", "name": "\ubc31\uc81c\uace0\ubd84\ub85c50\uae38", "name:en": "Baekjegobun-ro 50-gil", "name:ko": "\ubc31\uc81c\uace0\ubd84\ub85c50\uae38"}}, {"type": "way", "id": 172203041, "nodes": [999136632, 6546731634, 436812069, 436812065, 4680721607, 436812062, 436812061, 797051850, 797051851, 11229097873, 797051852, 797051853, 797051854, 7609153901, 2477237874, 4680721611, 4680721612, 2477239843, 6546731641, 798555855, 4680721615, 845976007, 797051857], "tags": {"bicycle": "designated", "cycleway:right": "opposite_track", "highway": "secondary", "name": "\uac15\ub3d9\ub300\ub85c", "name:en": "Gangdong-daero", "name:ko": "\uac15\ub3d9\ub300\ub85c", "name:ko-Latn": "Gangdong-daero", "oneway": "yes", "ref": "60", "surface": "asphalt"}}, {"type": "way", "id": 218855802, "nodes": [8436639424, 1809564267, 8116819797, 436869449, 1809560173], "tags": {"cycleway:both": "no", "highway": "primary", "lanes": "8", "name": "\uc62c\ub9bc\ud53d\ub85c", "name:en": "Olympic-ro", "name:ja": "\u30aa\u30ea\u30f3\u30d4\u30c3\u30af\u8def", "name:ko": "\uc62c\ub9bc\ud53d\ub85c", "name:ko-Latn": "Ollimpingno", "ref": "90", "review": "no", "smoothness": "excellent", "source": "NTIC", "surface": "asphalt"}}, {"type": "way", "id": 218899409, "nodes": [436859347, 4680041425, 6960603044, 11177272210, 2477248313], "tags": {"cycleway:both": "no", "highway": "primary", "lanes": "8", "maxspeed": "50", "name": "\uc62c\ub9bc\ud53d\ub85c", "name:en": "Olympic-ro", "name:ja": "\u30aa\u30ea\u30f3\u30d4\u30c3\u30af\u8def", "name:ko": "\uc62c\ub9bc\ud53d\ub85c", "name:ko-Latn": "Ollimpingno", "ref": "90", "review": "no", "source": "NTIC", "surface": "asphalt"}}, {"type": "way", "id": 239950022, "nodes": [2477232318, 2477232307, 2918341058, 10009448548, 2918341059, 2918341060], "tags": {"highway": "living_street"}}, {"type": "way", "id": 239950604, "nodes": [2477237876, 3856536065, 3856536120, 3856536122, 9664699430, 3856536071, 3856536273, 3856536124, 3856536126, 3856536068, 3856536128, 3856536130, 4191904191], "tags": {"check_date:surface": "2022-12-12", "highway": "residential", "name": "\uc131\uc548\ub85c3\uae38", "name:en": "Seongan-ro 3-gil", "name:ko": "\uc131\uc548\ub85c3\uae38", "smoothness": "good", "surface": "asphalt"}}, {"type": "way", "id": 369920697, "nodes": [1809560165, 4187713499], "tags": {"highway": "residential", "name": "\uc62c\ub9bc\ud53d\ub85c34\uae38", "name:en": "Olympic-ro 34-gil", "name:ko": "\uc62c\ub9bc\ud53d\ub85c34\uae38"}}, {"type": "way", "id": 369920698, "nodes": [1809578785, 1809584198, 1809584201, 1809584213, 1809613951, 1809613960, 6348622162, 6348622163, 1809613950, 1809613956, 6348622164, 6348622165, 1809584162, 1809578816, 1809578792], "tags": {"highway": "residential", "name": "\ubc31\uc81c\uace0\ubd84\ub85c50\uae38", "name:en": "Baekjegobun-ro 50-gil", "name:ko": "\ubc31\uc81c\uace0\ubd84\ub85c50\uae38"}}, {"type": "way", "id": 381969254, "nodes": [797051634, 3851762045, 5273519247, 3851762265, 3851762046, 3851762047, 3851762052, 3851762048], "tags": {"highway": "residential", "name": "\uac15\ub3d9\ub300\ub85c3\uae38", "name:en": "Gangdong-daero 3-gil", "name:ko": "\uac15\ub3d9\ub300\ub85c3\uae38"}}, {"type": "way", "id": 381969255, "nodes": [3851762049, 12129019960, 3851762050, 3851762053, 436877180], "tags": {"highway": "residential", "name": "\uac15\ub3d9\ub300\ub85c9\uae38", "name:en": "Gangdong-daero 9-gil", "name:ko": "\uac15\ub3d9\ub300\ub85c9\uae38", "surface": "asphalt"}}, {"type": "way", "id": 381969256, "nodes": [3851762046, 3851762262, 3851762261, 3851762258, 3851762050, 3958847217, 12129019920, 3851762051], "tags": {"highway": "residential", "name": "\uc62c\ub9bc\ud53d\ub85c45\uae38", "name:en": "Olympic-ro 45-gil", "name:ko": "\uc62c\ub9bc\ud53d\ub85c45\uae38"}}, {"type": "way", "id": 381969257, "nodes": [3851762052, 3851762260, 3851762257, 3851762053, 3851762055, 12129019948, 3851762054], "tags": {"highway": "residential", "name": "\uc62c\ub9bc\ud53d\ub85c47\uae38", "name:en": "Olympic-ro 47-gil", "name:ko": "\uc62c\ub9bc\ud53d\ub85c47\uae38", "surface": "asphalt"}}, {"type": "way", "id": 381969258, "nodes": [3851762055, 3851762056, 3958847217], "tags": {"highway": "residential", "name": "\uc62c\ub9bc\ud53d\ub85c47\uae38", "name:en": "Olympic-ro 47-gil", "name:ko": "\uc62c\ub9bc\ud53d\ub85c47\uae38"}}, {"type": "way", "id": 381969259, "nodes": [3851762257, 3851762258, 12129019949, 3851762259], "tags": {"highway": "residential", "name": "\uac15\ub3d9\ub300\ub85c7\uae38", "name:en": "Gangdong-daero 7-gil", "name:ko": "\uac15\ub3d9\ub300\ub85c7\uae38"}}, {"type": "way", "id": 381969260, "nodes": [3851762260, 3851762261, 12129019954, 797051631], "tags": {"highway": "residential", "name": "\uac15\ub3d9\ub300\ub85c5\uae38", "name:en": "Gangdong-daero 5-gil", "name:ko": "\uac15\ub3d9\ub300\ub85c5\uae38"}}, {"type": "way", "id": 381969261, "nodes": [3851762262, 12129019965, 3851762264], "tags": {"highway": "residential", "name": "\uac15\ub3d9\ub300\ub85c", "name:en": "Gangdong-daero", "name:ko": "\uac15\ub3d9\ub300\ub85c"}}, {"type": "way", "id": 381969262, "nodes": [3851762265, 3851762266, 3851762267, 12129019976, 3851762268], "tags": {"highway": "residential", "name": "\uac15\ub3d9\ub300\ub85c", "name:en": "Gangdong-daero", "name:ko": "\uac15\ub3d9\ub300\ub85c"}}, {"type": "way", "id": 382148873, "nodes": [3853477745, 3853477757, 3853477754, 3853477746, 3853477747, 3853477748, 3853477751, 3853477749], "tags": {"highway": "residential", "name": "\ud1a0\uc131\ub85c19\uae38", "name:en": "Toseong-ro 19-gil", "name:ko": "\ud1a0\uc131\ub85c19\uae38", "surface": "asphalt"}}, {"type": "way", "id": 382453975, "nodes": [2477237876, 3856536115, 3856536113, 3856536095, 3856536073, 3856536076, 436878399], "tags": {"highway": "residential", "name": "\uc62c\ub9bc\ud53d\ub85c48\uae38", "name:en": "Olympic-ro 48-gil", "name:ko": "\uc62c\ub9bc\ud53d\ub85c48\uae38"}}, {"type": "way", "id": 382453976, "nodes": [3856536065, 3856536067, 436855500], "tags": {"highway": "residential", "name": "\uc131\ub0b4\ub85c8\uae38", "name:en": "Seongnae-ro 8-gil", "name:ko": "\uc131\ub0b4\ub85c8\uae38", "surface": "asphalt"}}, {"type": "way", "id": 382453978, "nodes": [3856536068, 4191922825, 3856536070], "tags": {"highway": "residential", "name": "\uc131\ub0b4\ub85c12\uae38", "name:en": "Seongnae-ro 12-gil", "name:ko": "\uc131\ub0b4\ub85c12\uae38", "surface": "asphalt"}}, {"type": "way", "id": 382453979, "nodes": [3856536071, 4191922824, 436855499], "tags": {"highway": "residential", "name": "\uc131\ub0b4\ub85c10\uae38", "name:en": "Seongnae-ro 10-gil", "name:ko": "\uc131\ub0b4\ub85c10\uae38", "surface": "asphalt"}}, {"type": "way", "id": 382453989, "nodes": [11229097862, 5260056684, 3856536267, 3856536274, 3856536261, 3856536095], "tags": {"highway": "residential", "name": "\uc62c\ub9bc\ud53d\ub85c48\uae38", "name:en": "Olympic-ro 48-gil", "name:ko": "\uc62c\ub9bc\ud53d\ub85c48\uae38", "surface": "asphalt"}}, {"type": "way", "id": 382454002, "nodes": [3856536120, 3856536121], "tags": {"highway": "residential", "name": "\uc131\uc548\ub85c3\uae38", "name:en": "Seongan-ro 3-gil", "name:ko": "\uc131\uc548\ub85c3\uae38"}}, {"type": "way", "id": 382454003, "nodes": [3856536122, 3856536123], "tags": {"highway": "residential", "name": "\uc131\uc548\ub85c3\uae38", "name:en": "Seongan-ro 3-gil", "name:ko": "\uc131\uc548\ub85c3\uae38"}}, {"type": "way", "id": 382454004, "nodes": [3856536124, 3856536125], "tags": {"highway": "residential", "name": "\uc131\uc548\ub85c3\uae38", "name:en": "Seongan-ro 3-gil", "name:ko": "\uc131\uc548\ub85c3\uae38", "surface": "asphalt"}}, {"type": "way", "id": 382454005, "nodes": [3856536126, 3856536127], "tags": {"highway": "residential", "name": "\uc131\uc548\ub85c3\uae38", "name:en": "Seongan-ro 3-gil", "name:ko": "\uc131\uc548\ub85c3\uae38", "surface": "asphalt"}}, {"type": "way", "id": 382454006, "nodes": [3856536128, 3856536129], "tags": {"highway": "residential", "name": "\uc131\uc548\ub85c3\uae38", "name:en": "Seongan-ro 3-gil", "name:ko": "\uc131\uc548\ub85c3\uae38", "surface": "asphalt"}}, {"type": "way", "id": 382454007, "nodes": [3856536130, 3856536131], "tags": {"highway": "residential", "name": "\uc131\uc548\ub85c3\uae38", "name:en": "Seongan-ro 3-gil", "name:ko": "\uc131\uc548\ub85c3\uae38"}}, {"type": "way", "id": 382454020, "nodes": [3856536261, 4191922820], "tags": {"highway": "residential", "name": "\uc131\ub0b4\ub85c6\uae38", "name:en": "Seongnae-ro 6-gil", "name:ko": "\uc131\ub0b4\ub85c6\uae38"}}, {"type": "way", "id": 382454022, "nodes": [3856536267, 4191922822], "tags": {"highway": "residential", "name": "\uc131\ub0b4\ub85c6\uae38", "name:en": "Seongnae-ro 6-gil", "name:ko": "\uc131\ub0b4\ub85c6\uae38"}}, {"type": "way", "id": 382454023, "nodes": [3856536271, 3856536276, 3856536272, 3856536273], "tags": {"highway": "residential", "name": "\uc131\ub0b4\ub85c6\uac00\uae38", "name:en": "Seongnae-ro 6ga-gil", "name:ko": "\uc131\ub0b4\ub85c6\uac00\uae38"}}, {"type": "way", "id": 382454024, "nodes": [3856536274, 4191922821], "tags": {"highway": "residential", "name": "\uc131\ub0b4\ub85c6\uae38", "name:en": "Seongnae-ro 6-gil", "name:ko": "\uc131\ub0b4\ub85c6\uae38"}}, {"type": "way", "id": 382454025, "nodes": [3856536277, 3856536279, 3856536278], "tags": {"highway": "residential", "name": "\uc131\ub0b4\ub85c6\uac00\uae38", "name:en": "Seongnae-ro 6ga-gil", "name:ko": "\uc131\ub0b4\ub85c6\uac00\uae38"}}, {"type": "way", "id": 382454026, "nodes": [3856536279, 3856536280, 3856536281], "tags": {"highway": "residential", "name": "\uc131\ub0b4\ub85c14\uae38", "name:en": "Seongnae-ro 14-gil", "name:ko": "\uc131\ub0b4\ub85c14\uae38", "surface": "asphalt"}}, {"type": "way", "id": 418339420, "nodes": [4187713500, 1809564300], "tags": {"highway": "residential", "name": "\uc624\uae08\ub85c11\uae38", "name:en": "Ogeum-ro 11-gil", "name:ko": "\uc624\uae08\ub85c11\uae38", "surface": "asphalt"}}, {"type": "way", "id": 418339421, "nodes": [1809584190, 1809613953, 1809613958, 1809578813, 1809584162, 6348622166, 436866941], "tags": {"highway": "residential", "name": "\uc704\ub840\uc131\ub300\ub85c4\uae38", "name:en": "Wiryeseong-daero 4-gil", "name:ko": "\uc704\ub840\uc131\ub300\ub85c4\uae38"}}, {"type": "way", "id": 418992341, "nodes": [4191904191, 3856536263, 3856536280, 3856536269, 7609153889, 436812039, 2477237874], "tags": {"highway": "residential", "name": "\uc131\ub0b4\ub85c14\uae38", "name:en": "Seongnae-ro 14-gil", "name:ko": "\uc131\ub0b4\ub85c14\uae38", "surface": "asphalt"}}, {"type": "way", "id": 418994877, "nodes": [4191922820, 9664699415, 9664699424, 9664699423, 3856536272, 3856536278, 3856536263, 3856536264], "tags": {"highway": "residential", "name": "\uc131\ub0b4\ub85c6\uac00\uae38", "name:en": "Seongnae-ro 6ga-gil", "name:ko": "\uc131\ub0b4\ub85c6\uac00\uae38", "surface": "asphalt"}}, {"type": "way", "id": 418994880, "nodes": [4191922821, 9664699426, 3856536276], "tags": {"highway": "residential", "name": "\uc131\ub0b4\ub85c6\ub098\uae38", "name:en": "Seongnae-ro 6na-gil", "name:ko": "\uc131\ub0b4\ub85c6\ub098\uae38"}}, {"type": "way", "id": 418994882, "nodes": [4191922822, 3856536271, 3856536277, 3856536269, 3856536270], "tags": {"highway": "residential", "name": "\uc131\ub0b4\ub85c6\ub2e4\uae38", "name:en": "Seongnae-ro 6da-gil", "name:ko": "\uc131\ub0b4\ub85c6\ub2e4\uae38"}}, {"type": "way", "id": 426094556, "nodes": [4254083554, 4254083553], "tags": {"bridge": "yes", "bridge:structure": "beam", "cycleway:both": "no", "highway": "primary", "lanes": "8", "layer": "1", "maxspeed": "50", "name": "\uc62c\ub9bc\ud53d\ub85c", "name:en": "Olympic-ro", "name:ja": "\u30aa\u30ea\u30f3\u30d4\u30c3\u30af \u8def", "name:ko": "\uc62c\ub9bc\ud53d\ub85c", "name:ko-Latn": "Ollimpingno", "ref": "90", "review": "no", "source": "NTIC", "surface": "asphalt"}}, {"type": "way", "id": 426094557, "nodes": [4254083553, 2918341060, 2477230545, 11177272212, 436869448, 4681593288, 11177272211, 4636654767, 11177272203, 6960603045, 436859347], "tags": {"cycleway:both": "no", "highway": "primary", "maxspeed": "50", "name": "\uc62c\ub9bc\ud53d\ub85c", "name:en": "Olympic-ro", "name:ja": "\u30aa\u30ea\u30f3\u30d4\u30c3\u30af\u8def", "name:ko": "\uc62c\ub9bc\ud53d\ub85c", "name:ko-Latn": "Ollimpingno", "ref": "90", "review": "no", "source": "NTIC", "surface": "asphalt"}}, {"type": "way", "id": 469302655, "nodes": [4636654766, 4636670595, 4636670593, 4636654762, 8946638422, 4636654767], "tags": {"highway": "residential"}}, {"type": "way", "id": 469302657, "nodes": [4636654768, 4636654766, 8116864617, 8116819807, 8116864633, 4636654769], "tags": {"highway": "residential"}}, {"type": "way", "id": 473966575, "nodes": [4679959424, 11177272192, 845894226, 9079503585], "tags": {"highway": "secondary", "name": "\uc704\ub840\uc131\ub300\ub85c", "name:en": "Wiryeseong-daero", "name:ko": "\uc704\ub840\uc131\ub300\ub85c", "ncat": "\uad11\uc5ed\uc2dc\ub3c4\ub85c", "official_ref": "4237", "oneway": "yes", "review": "no", "source": "NTIC", "surface": "asphalt"}}, {"type": "way", "id": 516725205, "nodes": [10777963309, 999136632], "tags": {"cycleway:both": "no", "highway": "primary", "name": "\uc62c\ub9bc\ud53d\ub85c", "name:en": "Olympic-ro", "name:ja": "\u30aa\u30ea\u30f3\u30d4\u30c3\u30af \u8def", "name:ko": "\uc62c\ub9bc\ud53d\ub85c", "name:ko-Latn": "Ollimpingno", "ref": "90", "surface": "asphalt"}}, {"type": "way", "id": 516725206, "nodes": [3969132982, 3856535938, 4680721613, 3856535907, 11229084224, 798555856, 6546731640, 2477239844, 3856536062, 11229097839, 11229097842, 436812039, 7609153902, 11229097850, 436812044, 797051901, 11229097869, 11229097871, 11229097868, 797051904, 797051907, 797051908, 797051909, 797051910, 6546731633, 10777963310, 10777963309], "tags": {"bicycle": "designated", "cycleway:right": "opposite_track", "highway": "secondary", "name": "\uac15\ub3d9\ub300\ub85c", "name:en": "Gangdong-daero", "name:ko": "\uac15\ub3d9\ub300\ub85c", "name:ko-Latn": "Gangdong-daero", "oneway": "yes", "ref": "60", "surface": "asphalt"}}, {"type": "way", "id": 516725215, "nodes": [8442852754, 4680822159, 2477231265, 8357174039, 4254083554], "tags": {"cycleway:both": "no", "highway": "primary", "lanes": "8", "maxspeed": "50", "name": "\uc62c\ub9bc\ud53d\ub85c", "name:en": "Olympic-ro", "name:ja": "\u30aa\u30ea\u30f3\u30d4\u30c3\u30af \u8def", "name:ko": "\uc62c\ub9bc\ud53d\ub85c", "name:ko-Latn": "Ollimpingno", "ref": "90", "surface": "asphalt"}}, {"type": "way", "id": 545695193, "nodes": [5273854569, 5273854568], "tags": {"highway": "tertiary_link", "surface": "asphalt"}}, {"type": "way", "id": 549131658, "nodes": [5304584194, 436869430, 436869431, 436869432, 436869433, 5304584193, 6458482380, 5159098835, 4659574362, 414684881, 4664955077, 4664955078, 4664955075, 4664955074, 4664955071, 4664955069, 4664955068, 2477228800, 4664955066, 4659574359, 436869440, 436869441], "tags": {"highway": "residential", "name": "\uc62c\ub9bc\ud53d\ub85c37\uae38", "name:en": "Olympic-ro 37-gil", "name:ko": "\uc62c\ub9bc\ud53d\ub85c37\uae38", "name:ko-Latn": "Olympic-ro 37-gil", "ncat": "\uad11\uc5ed\uc2dc\ub3c4\ub85c", "review": "no", "source": "NTIC", "surface": "asphalt"}}, {"type": "way", "id": 867830209, "nodes": [436859347, 2477228825, 11177272206, 4636654769, 8116864631, 2477229063], "tags": {"highway": "tertiary", "name": "\uc62c\ub9bc\ud53d\ub85c35\uae38", "name:en": "Olympic-ro 35-gil", "name:ko": "\uc62c\ub9bc\ud53d\ub85c35\uae38", "ncat": "\uad11\uc5ed\uc2dc\ub3c4\ub85c", "review": "no", "source": "NTIC"}}, {"type": "way", "id": 908111137, "nodes": [436877179, 6546731616, 5804563290, 436878399], "tags": {"cycleway:both": "no", "highway": "primary", "lanes": "6", "name": "\uc62c\ub9bc\ud53d\ub85c", "name:en": "Olympic-ro", "name:ja": "\u30aa\u30ea\u30f3\u30d4\u30c3\u30af\u8def", "name:ko": "\uc62c\ub9bc\ud53d\ub85c", "oneway": "no", "ref": "90", "smoothness": "excellent", "surface": "asphalt"}}, {"type": "way", "id": 908242253, "nodes": [10777963309, 6546731632, 3851762049, 3851762259, 797051631, 3851762264, 9533959333, 3851762268, 797051634, 8693812050, 9533959335, 797051635, 797051636, 797051637, 797051638, 797051639], "tags": {"bicycle": "designated", "cycleway:right": "opposite_track", "highway": "secondary", "name": "\uac15\ub3d9\ub300\ub85c", "name:en": "Gangdong-daero", "name:ko": "\uac15\ub3d9\ub300\ub85c", "name:ko-Latn": "Gangdong-daero", "oneway": "yes", "ref": "60", "surface": "asphalt"}}, {"type": "way", "id": 908313110, "nodes": [797051489, 436812087, 436812084, 436812078, 436812075, 6546731631, 999136632], "tags": {"bicycle": "designated", "cycleway:right": "opposite_track", "highway": "secondary", "name": "\uac15\ub3d9\ub300\ub85c", "name:en": "Gangdong-daero", "name:ko": "\uac15\ub3d9\ub300\ub85c", "name:ko-Latn": "Gangdong-daero", "oneway": "yes", "ref": "60", "surface": "asphalt"}}, {"type": "way", "id": 908608589, "nodes": [2477248313, 8436639417, 8436639418, 8436639419, 8969922174, 8436639420, 8436639421, 8436639422, 8436639423, 8436639424], "tags": {"highway": "primary", "name": "\uc62c\ub9bc\ud53d\ub85c", "name:en": "Olympic-ro", "name:ja": "\u30aa\u30ea\u30f3\u30d4\u30c3\u30af\u8def", "name:ko": "\uc62c\ub9bc\ud53d\ub85c", "name:ko-Latn": "Ollimpingno", "oneway": "yes", "ref": "90", "surface": "asphalt"}}, {"type": "way", "id": 908608590, "nodes": [8436639424, 8436639415, 8969922173, 2346858828], "tags": {"highway": "primary", "name": "\uc62c\ub9bc\ud53d\ub85c", "name:en": "Olympic-ro", "name:ja": "\u30aa\u30ea\u30f3\u30d4\u30c3\u30af\u8def", "name:ko": "\uc62c\ub9bc\ud53d\ub85c", "name:ko-Latn": "Ollimpingno", "ref": "90", "review": "no", "source": "NTIC", "surface": "asphalt"}}, {"type": "way", "id": 908608591, "nodes": [2346858828, 8969922170, 8969922171, 11177272202, 8436639416, 2477248313], "tags": {"cycleway:both": "no", "highway": "primary", "name": "\uc62c\ub9bc\ud53d\ub85c", "name:en": "Olympic-ro", "name:ja": "\u30aa\u30ea\u30f3\u30d4\u30c3\u30af\u8def", "name:ko": "\uc62c\ub9bc\ud53d\ub85c", "name:ko-Latn": "Ollimpingno", "ref": "90", "review": "no", "source": "NTIC", "surface": "asphalt"}}, {"type": "way", "id": 909315380, "nodes": [999136632, 6546731636, 8550523624, 8442852754], "tags": {"highway": "primary", "name": "\uc62c\ub9bc\ud53d\ub85c", "name:en": "Olympic-ro", "name:ja": "\u30aa\u30ea\u30f3\u30d4\u30c3\u30af \u8def", "name:ko": "\uc62c\ub9bc\ud53d\ub85c", "name:ko-Latn": "Ollimpingno", "ref": "90", "surface": "asphalt"}}, {"type": "way", "id": 909315384, "nodes": [797051279, 10923903160, 3583849859, 797051476, 9533959342, 797051479, 797051482, 436878439, 797051486, 797051489], "tags": {"highway": "trunk_link", "oneway": "yes", "surface": "asphalt"}}, {"type": "way", "id": 920941852, "nodes": [8550523624, 8550523623, 8550523622, 5260056212, 8550523621, 8969922149, 436812069], "tags": {"destination": "\uc11c\ud558\ub0a8IC", "highway": "secondary_link", "oneway": "yes"}}, {"type": "way", "id": 1034985428, "nodes": [797051482, 9533959343, 9533959344, 9533959345, 9533959336], "tags": {"highway": "tertiary", "oneway": "yes"}}, {"type": "way", "id": 1034985429, "nodes": [9533959336, 9533959337, 9533959338, 436878439], "tags": {"highway": "tertiary", "name": "\uac15\ub3d9\ub300\ub85c2\uae38", "name:en": "Gangdong-daero 2-gil", "name:ko": "\uac15\ub3d9\ub300\ub85c2\uae38", "oneway": "yes"}}, {"type": "way", "id": 1206205735, "nodes": [11177272192, 11177272193, 11177272194, 11177272195, 11177272196], "tags": {"highway": "secondary_link", "oneway": "yes"}}, {"type": "way", "id": 1206205736, "nodes": [845893207, 11177272197, 11177272198, 11177272199, 11177272224, 11177272200, 11177272201, 11177272202], "tags": {"highway": "secondary_link", "oneway": "yes"}}, {"type": "way", "id": 1206205737, "nodes": [11177272203, 11177272204, 11177272205, 2477228825], "tags": {"highway": "secondary_link", "oneway": "yes"}}, {"type": "way", "id": 1206205738, "nodes": [11177272206, 11177272207, 11177272208, 11177272209, 11177272210], "tags": {"highway": "secondary_link", "oneway": "yes"}}, {"type": "way", "id": 1206205739, "nodes": [436869441, 5896568486, 5896568485, 5896568487, 436869447, 10009448544, 5896568488, 11177272211], "tags": {"highway": "residential", "name": "\uc62c\ub9bc\ud53d\ub85c37\uae38", "name:en": "Olympic-ro 37-gil", "name:ko": "\uc62c\ub9bc\ud53d\ub85c37\uae38", "name:ko-Latn": "Olympic-ro 37-gil", "ncat": "\uad11\uc5ed\uc2dc\ub3c4\ub85c", "oneway": "yes", "review": "no", "source": "NTIC", "surface": "asphalt"}}, {"type": "way", "id": 1206205740, "nodes": [11177272212, 11177272213, 11177272214, 11177272215, 11177272216, 11177272217, 11177272218, 11177272219, 11177272220, 436869441], "tags": {"highway": "residential", "oneway": "yes"}}, {"type": "way", "id": 1206205741, "nodes": [8436639424, 11177272228, 11177272229, 11177272230, 11177272231, 11177272232, 11177272233], "tags": {"highway": "secondary_link", "oneway": "yes"}}, {"type": "way", "id": 1212063832, "nodes": [11229097839, 11229097838, 11229097840, 11229097841, 11229097842], "tags": {"highway": "secondary_link", "oneway": "yes"}}, {"type": "way", "id": 1212063838, "nodes": [11229097850, 11229097851, 11229097874, 11229097852, 11229097853], "tags": {"highway": "secondary_link", "oneway": "yes"}}, {"type": "way", "id": 1212063839, "nodes": [11229097854, 11229097855, 11229097856, 11229097857, 6546731616], "tags": {"highway": "secondary_link", "oneway": "yes"}}, {"type": "way", "id": 1212063840, "nodes": [11229097858, 11229097859, 11229097860, 11229097862, 11229097861, 11229097854], "tags": {"highway": "secondary_link", "oneway": "yes"}}, {"type": "way", "id": 1212063841, "nodes": [436877179, 11229097863, 11229097864, 11229097865], "tags": {"highway": "secondary", "lanes": "3", "name": "\uac15\ub3d9\ub300\ub85c", "name:en": "Gangdong-daero", "name:ko": "\uac15\ub3d9\ub300\ub85c", "name:ko-Latn": "Gangdong-daero", "oneway": "yes", "smoothness": "excellent", "surface": "asphalt"}}, {"type": "way", "id": 1212063842, "nodes": [11229097871, 11229097872, 11229097873], "tags": {"highway": "secondary"}}, {"type": "way", "id": 1212063843, "nodes": [11229097865, 11229097876, 11229097866, 11229097870, 11229097871], "tags": {"highway": "secondary", "lanes": "2", "name": "\uac15\ub3d9\ub300\ub85c", "name:en": "Gangdong-daero", "name:ko": "\uac15\ub3d9\ub300\ub85c", "name:ko-Latn": "Gangdong-daero", "ncat": "\uad11\uc5ed\uc2dc\ub3c4\ub85c", "oneway": "yes", "review": "no", "smoothness": "excellent", "source": "NTIC", "surface": "asphalt"}}, {"type": "way", "id": 1212063847, "nodes": [11229097879, 2477231277, 3856536094, 11229097854, 6546731627, 436877179], "tags": {"highway": "secondary", "lanes": "5", "name": "\uac15\ub3d9\ub300\ub85c", "name:en": "Gangdong-daero", "name:ko": "\uac15\ub3d9\ub300\ub85c", "name:ko-Latn": "Gangdong-daero", "oneway": "yes", "smoothness": "excellent", "surface": "asphalt"}}, {"type": "way", "id": 1212063848, "nodes": [436812044, 436812154, 999136618], "tags": {"highway": "secondary", "lanes": "1", "name": "\uac15\ub3d9\ub300\ub85c", "name:en": "Gangdong-daero", "name:ko": "\uac15\ub3d9\ub300\ub85c", "name:ko-Latn": "Gangdong-daero", "ncat": "\uad11\uc5ed\uc2dc\ub3c4\ub85c", "oneway": "yes", "review": "no", "smoothness": "excellent", "source": "NTIC", "surface": "asphalt"}}, {"type": "way", "id": 1212063849, "nodes": [11229097865, 11229097880, 11229097881, 436811817], "tags": {"highway": "secondary_link", "oneway": "yes"}}]}