{"version": 0.6, "generator": "Overpass API 0.7.62.5 1bd436f1", "osm3s": {"timestamp_osm_base": "2025-05-15T00:21:19Z", "copyright": "The data included in this document is from www.openstreetmap.org. The data is made available under ODbL."}, "elements": [{"type": "node", "id": 414683310, "lat": 37.5594768, "lon": 126.8581629, "tags": {"junction": "yes"}}, {"type": "node", "id": 436693463, "lat": 37.5544, "lon": 126.86681}, {"type": "node", "id": 436693464, "lat": 37.55474, "lon": 126.8662}, {"type": "node", "id": 436693465, "lat": 37.5551, "lon": 126.86574}, {"type": "node", "id": 436693466, "lat": 37.55556, "lon": 126.86517}, {"type": "node", "id": 436693467, "lat": 37.5560635, "lon": 126.8645378}, {"type": "node", "id": 436760154, "lat": 37.5603837, "lon": 126.8910654}, {"type": "node", "id": 436760155, "lat": 37.5615037, "lon": 126.889044}, {"type": "node", "id": 436760156, "lat": 37.5638015, "lon": 126.8851542}, {"type": "node", "id": 436760157, "lat": 37.5674736, "lon": 126.878713}, {"type": "node", "id": 436760158, "lat": 37.5709505, "lon": 126.8727453}, {"type": "node", "id": 436764032, "lat": 37.5567308, "lon": 126.8721089}, {"type": "node", "id": 436764033, "lat": 37.5587458, "lon": 126.869732}, {"type": "node", "id": 436764035, "lat": 37.5601071, "lon": 126.8679438}, {"type": "node", "id": 436764036, "lat": 37.5611228, "lon": 126.8663479}, {"type": "node", "id": 436809361, "lat": 37.5762258, "lon": 126.8663146}, {"type": "node", "id": 436809431, "lat": 37.5605, "lon": 126.86223}, {"type": "node", "id": 436809433, "lat": 37.56228, "lon": 126.85894}, {"type": "node", "id": 436809435, "lat": 37.5635866, "lon": 126.8565449}, {"type": "node", "id": 436824835, "lat": 37.5672965, "lon": 126.8509208}, {"type": "node", "id": 436830183, "lat": 37.57681, "lon": 126.88016}, {"type": "node", "id": 436830187, "lat": 37.57668, "lon": 126.88006}, {"type": "node", "id": 436830188, "lat": 37.57654, "lon": 126.88006}, {"type": "node", "id": 436830189, "lat": 37.57636, "lon": 126.88017}, {"type": "node", "id": 436830190, "lat": 37.57631, "lon": 126.88023}, {"type": "node", "id": 436830192, "lat": 37.57523, "lon": 126.8817}, {"type": "node", "id": 436830193, "lat": 37.5745, "lon": 126.88268}, {"type": "node", "id": 436830195, "lat": 37.57407, "lon": 126.88326}, {"type": "node", "id": 436830198, "lat": 37.57392, "lon": 126.88333}, {"type": "node", "id": 436830199, "lat": 37.573, "lon": 126.88329}, {"type": "node", "id": 436830200, "lat": 37.57254, "lon": 126.88319}, {"type": "node", "id": 436830201, "lat": 37.57238, "lon": 126.88311}, {"type": "node", "id": 436830203, "lat": 37.57198, "lon": 126.88277}, {"type": "node", "id": 436830206, "lat": 37.57038, "lon": 126.88133}, {"type": "node", "id": 436830207, "lat": 37.5694226, "lon": 126.8805142}, {"type": "node", "id": 436847628, "lat": 37.5651523, "lon": 126.8537103}, {"type": "node", "id": 436868136, "lat": 37.5616272, "lon": 126.8601466}, {"type": "node", "id": 436873140, "lat": 37.5580842, "lon": 126.8642664}, {"type": "node", "id": 436873141, "lat": 37.5589091, "lon": 126.8651781}, {"type": "node", "id": 436881126, "lat": 37.56385, "lon": 126.85607}, {"type": "node", "id": 436881128, "lat": 37.56596, "lon": 126.85251}, {"type": "node", "id": 436881129, "lat": 37.56717, "lon": 126.85106}, {"type": "node", "id": 436881130, "lat": 37.5675066, "lon": 126.8507095}, {"type": "node", "id": 436881131, "lat": 37.56844, "lon": 126.84955}, {"type": "node", "id": 436881132, "lat": 37.5688, "lon": 126.84905}, {"type": "node", "id": 436881133, "lat": 37.56904, "lon": 126.8486}, {"type": "node", "id": 436881134, "lat": 37.56919, "lon": 126.84827}, {"type": "node", "id": 436881135, "lat": 37.56945, "lon": 126.84743}, {"type": "node", "id": 436881136, "lat": 37.57004, "lon": 126.84522}, {"type": "node", "id": 436881137, "lat": 37.57086, "lon": 126.84218}, {"type": "node", "id": 436881138, "lat": 37.5709772, "lon": 126.8418046, "tags": {"junction": "yes", "name": "\ub300\uc544\ub3d9\uc2e0\uc544\ud30c\ud2b8\uc55e", "name:en": "Daeadongsin Apt. Front", "name:ko": "\ub300\uc544\ub3d9\uc2e0\uc544\ud30c\ud2b8\uc55e", "name:ko-Latn": "Daeadongsinapateuap"}}, {"type": "node", "id": 449464861, "lat": 37.5708166, "lon": 126.8824445}, {"type": "node", "id": 449464863, "lat": 37.5705606, "lon": 126.882348}, {"type": "node", "id": 449464865, "lat": 37.5702979, "lon": 126.8822343}, {"type": "node", "id": 449464867, "lat": 37.5700105, "lon": 126.8820906}, {"type": "node", "id": 449464869, "lat": 37.5698276, "lon": 126.8819124}, {"type": "node", "id": 449464871, "lat": 37.5696371, "lon": 126.8816292}, {"type": "node", "id": 449464873, "lat": 37.569365, "lon": 126.8813717}, {"type": "node", "id": 449464875, "lat": 37.5690249, "lon": 126.8811915}, {"type": "node", "id": 449464877, "lat": 37.5686439, "lon": 126.8810112}, {"type": "node", "id": 449464879, "lat": 37.5683854, "lon": 126.8808653}, {"type": "node", "id": 449464881, "lat": 37.5682493, "lon": 126.8808653}, {"type": "node", "id": 449464883, "lat": 37.5680996, "lon": 126.8809511}, {"type": "node", "id": 449464885, "lat": 37.5679432, "lon": 126.8812344}, {"type": "node", "id": 449464887, "lat": 37.56712, "lon": 126.8825132}, {"type": "node", "id": 449464888, "lat": 37.5655212, "lon": 126.8850023}, {"type": "node", "id": 449464894, "lat": 37.5643718, "lon": 126.8867569}, {"type": "node", "id": 449464896, "lat": 37.5642417, "lon": 126.8869572}, {"type": "node", "id": 449464898, "lat": 37.564218, "lon": 126.887102}, {"type": "node", "id": 449464900, "lat": 37.564235, "lon": 126.8871743}, {"type": "node", "id": 449464902, "lat": 37.5642691, "lon": 126.8872159}, {"type": "node", "id": 449464904, "lat": 37.5643718, "lon": 126.8872901}, {"type": "node", "id": 449464906, "lat": 37.5645211, "lon": 126.8873342}, {"type": "node", "id": 449464908, "lat": 37.5646768, "lon": 126.8874044}, {"type": "node", "id": 449464910, "lat": 37.5649192, "lon": 126.8875894}, {"type": "node", "id": 449464912, "lat": 37.5654495, "lon": 126.8882755}, {"type": "node", "id": 449464914, "lat": 37.5662808, "lon": 126.8893083}, {"type": "node", "id": 449464916, "lat": 37.5663505, "lon": 126.8893643}, {"type": "node", "id": 449464918, "lat": 37.5664792, "lon": 126.8894643}, {"type": "node", "id": 449464920, "lat": 37.566605, "lon": 126.8894705}, {"type": "node", "id": 449464922, "lat": 37.5667448, "lon": 126.8894449}, {"type": "node", "id": 449464924, "lat": 37.5674829, "lon": 126.8889381}, {"type": "node", "id": 449464926, "lat": 37.5683194, "lon": 126.8883875}, {"type": "node", "id": 449464927, "lat": 37.5688344, "lon": 126.8880332}, {"type": "node", "id": 449464929, "lat": 37.5690113, "lon": 126.8878262}, {"type": "node", "id": 449464931, "lat": 37.5691201, "lon": 126.8874743}, {"type": "node", "id": 449464935, "lat": 37.5695011, "lon": 126.8860752}, {"type": "node", "id": 449464938, "lat": 37.5696775, "lon": 126.8857065}, {"type": "node", "id": 449464939, "lat": 37.5715811, "lon": 126.8839531}, {"type": "node", "id": 449468506, "lat": 37.5662498, "lon": 126.8894232}, {"type": "node", "id": 449468508, "lat": 37.5660483, "lon": 126.8893062}, {"type": "node", "id": 449468513, "lat": 37.5657251, "lon": 126.8889812}, {"type": "node", "id": 449468515, "lat": 37.5652961, "lon": 126.8885545}, {"type": "node", "id": 449468517, "lat": 37.5648859, "lon": 126.8881861}, {"type": "node", "id": 449468519, "lat": 37.5645948, "lon": 126.8879739}, {"type": "node", "id": 449468521, "lat": 37.5643935, "lon": 126.8879132}, {"type": "node", "id": 449468523, "lat": 37.5641365, "lon": 126.8879783}, {"type": "node", "id": 449468525, "lat": 37.5636094, "lon": 126.8880231}, {"type": "node", "id": 449468527, "lat": 37.5627806, "lon": 126.888022}, {"type": "node", "id": 449471230, "lat": 37.5681765, "lon": 126.8884766}, {"type": "node", "id": 449471589, "lat": 37.5713817, "lon": 126.8841425}, {"type": "node", "id": 449471997, "lat": 37.5655224, "lon": 126.8866721}, {"type": "node", "id": 449471999, "lat": 37.5654881, "lon": 126.8869066}, {"type": "node", "id": 449472001, "lat": 37.56552, "lon": 126.8870079}, {"type": "node", "id": 449472005, "lat": 37.5664311, "lon": 126.887919}, {"type": "node", "id": 449472007, "lat": 37.5666719, "lon": 126.8881601}, {"type": "node", "id": 449472009, "lat": 37.5668712, "lon": 126.8883286}, {"type": "node", "id": 449472010, "lat": 37.5670381, "lon": 126.88832}, {"type": "node", "id": 449472012, "lat": 37.5675477, "lon": 126.8880612}, {"type": "node", "id": 449472537, "lat": 37.569098, "lon": 126.8857906}, {"type": "node", "id": 449472539, "lat": 37.5700861, "lon": 126.8840324}, {"type": "node", "id": 449472540, "lat": 37.5701793, "lon": 126.8838748}, {"type": "node", "id": 449472542, "lat": 37.5701912, "lon": 126.883732}, {"type": "node", "id": 449472543, "lat": 37.5701252, "lon": 126.8835604}, {"type": "node", "id": 449472545, "lat": 37.5687684, "lon": 126.8821943}, {"type": "node", "id": 449472547, "lat": 37.568558, "lon": 126.8820187}, {"type": "node", "id": 449472548, "lat": 37.568413, "lon": 126.8820047}, {"type": "node", "id": 449472550, "lat": 37.568282, "lon": 126.8820959}, {"type": "node", "id": 449472636, "lat": 37.5691529, "lon": 126.8871646}, {"type": "node", "id": 449472640, "lat": 37.5691826, "lon": 126.8870579}, {"type": "node", "id": 449472899, "lat": 37.5674555, "lon": 126.8854883}, {"type": "node", "id": 449473088, "lat": 37.5691943, "lon": 126.8826424}, {"type": "node", "id": 449473090, "lat": 37.5661056, "lon": 126.8875989}, {"type": "node", "id": 449473451, "lat": 37.5691197, "lon": 126.8827616}, {"type": "node", "id": 449473563, "lat": 37.5661782, "lon": 126.8874743}, {"type": "node", "id": 449473568, "lat": 37.5666664, "lon": 126.8847273}, {"type": "node", "id": 601637062, "lat": 37.5903874, "lon": 126.8069382}, {"type": "node", "id": 601637083, "lat": 37.5893999, "lon": 126.8094676}, {"type": "node", "id": 601637084, "lat": 37.5893571, "lon": 126.8100328}, {"type": "node", "id": 601637094, "lat": 37.5917064, "lon": 126.804904}, {"type": "node", "id": 601637164, "lat": 37.5902725, "lon": 126.8072198}, {"type": "node", "id": 601637165, "lat": 37.5901302, "lon": 126.8075872}, {"type": "node", "id": 601637166, "lat": 37.5900409, "lon": 126.8078743}, {"type": "node", "id": 601637167, "lat": 37.5898582, "lon": 126.8083838}, {"type": "node", "id": 601637168, "lat": 37.5895988, "lon": 126.8090517}, {"type": "node", "id": 601637169, "lat": 37.5890895, "lon": 126.8102498}, {"type": "node", "id": 601637173, "lat": 37.5895228, "lon": 126.809564}, {"type": "node", "id": 601637174, "lat": 37.5897334, "lon": 126.8090519}, {"type": "node", "id": 601637175, "lat": 37.5900292, "lon": 126.8082144}, {"type": "node", "id": 601637176, "lat": 37.5904207, "lon": 126.8072131}, {"type": "node", "id": 601637179, "lat": 37.5907058, "lon": 126.8066503}, {"type": "node", "id": 601637180, "lat": 37.5909724, "lon": 126.8061707}, {"type": "node", "id": 601703820, "lat": 37.5825636, "lon": 126.8235607}, {"type": "node", "id": 601703936, "lat": 37.5837527, "lon": 126.8208363}, {"type": "node", "id": 601703942, "lat": 37.5833969, "lon": 126.8216509}, {"type": "node", "id": 601703944, "lat": 37.5829462, "lon": 126.822638}, {"type": "node", "id": 601703948, "lat": 37.582147, "lon": 126.8246121}, {"type": "node", "id": 601703957, "lat": 37.5769591, "lon": 126.8386227}, {"type": "node", "id": 601703959, "lat": 37.576601, "lon": 126.8394554}, {"type": "node", "id": 601703965, "lat": 37.5761302, "lon": 126.8404371}, {"type": "node", "id": 601703968, "lat": 37.5758048, "lon": 126.8410633}, {"type": "node", "id": 601703970, "lat": 37.5754049, "lon": 126.8417697}, {"type": "node", "id": 601704002, "lat": 37.5755285, "lon": 126.841873}, {"type": "node", "id": 601704008, "lat": 37.5759266, "lon": 126.8411802}, {"type": "node", "id": 601704011, "lat": 37.5762756, "lon": 126.8405472}, {"type": "node", "id": 601704014, "lat": 37.576741, "lon": 126.8395356}, {"type": "node", "id": 601704017, "lat": 37.5771134, "lon": 126.838699}, {"type": "node", "id": 601704028, "lat": 37.5817884, "lon": 126.8260392, "tags": {"destination:lang:ja": "88JCT", "destination:lang:zh-Hans": "88\u5206\u5c94", "destination:lang:zh-Hant": "88\u5206\u5c94", "highway": "motorway_junction", "name": "88\ubd84\uae30\uc810", "name:en": "88 JC", "name:ko": "88\ubd84\uae30\uc810", "ref": "8"}}, {"type": "node", "id": 601704031, "lat": 37.582181, "lon": 126.8249339}, {"type": "node", "id": 601704037, "lat": 37.5827586, "lon": 126.8234032}, {"type": "node", "id": 601704040, "lat": 37.5831078, "lon": 126.8226058}, {"type": "node", "id": 601704043, "lat": 37.5836689, "lon": 126.8213505}, {"type": "node", "id": 601704046, "lat": 37.5839235, "lon": 126.8207741}, {"type": "node", "id": 653186424, "lat": 37.5618958, "lon": 126.8879887}, {"type": "node", "id": 653191660, "lat": 37.5613392, "lon": 126.8889457}, {"type": "node", "id": 796108844, "lat": 37.5615066, "lon": 126.8659106}, {"type": "node", "id": 796108848, "lat": 37.5635329, "lon": 126.8625149}, {"type": "node", "id": 796108855, "lat": 37.5670656, "lon": 126.8563736}, {"type": "node", "id": 796110768, "lat": 37.5683335, "lon": 126.853948}, {"type": "node", "id": 796110778, "lat": 37.5624616, "lon": 126.8639927}, {"type": "node", "id": 798566628, "lat": 37.554477, "lon": 126.8750645}, {"type": "node", "id": 798566629, "lat": 37.5558593, "lon": 126.8733487}, {"type": "node", "id": 798566630, "lat": 37.5583701, "lon": 126.8704799}, {"type": "node", "id": 798566631, "lat": 37.5596951, "lon": 126.8687783}, {"type": "node", "id": 798566632, "lat": 37.5602267, "lon": 126.8680702}, {"type": "node", "id": 798566633, "lat": 37.5609666, "lon": 126.8668095}, {"type": "node", "id": 798566739, "lat": 37.5549892, "lon": 126.8746962}, {"type": "node", "id": 798566740, "lat": 37.5551416, "lon": 126.8745385}, {"type": "node", "id": 798566741, "lat": 37.5555196, "lon": 126.874146}, {"type": "node", "id": 798566742, "lat": 37.5559979, "lon": 126.873494}, {"type": "node", "id": 798566744, "lat": 37.5566151, "lon": 126.8726668}, {"type": "node", "id": 798566745, "lat": 37.5568362, "lon": 126.8722516}, {"type": "node", "id": 798566746, "lat": 37.5550464, "lon": 126.8740746}, {"type": "node", "id": 798567737, "lat": 37.5563341, "lon": 126.8695599}, {"type": "node", "id": 798567738, "lat": 37.5558338, "lon": 126.8705137}, {"type": "node", "id": 798568085, "lat": 37.5560362, "lon": 126.8688877}, {"type": "node", "id": 798568087, "lat": 37.5547494, "lon": 126.870202}, {"type": "node", "id": 798568104, "lat": 37.5555581, "lon": 126.8676481}, {"type": "node", "id": 798568109, "lat": 37.5559933, "lon": 126.8685301}, {"type": "node", "id": 798568110, "lat": 37.5560246, "lon": 126.8685973}, {"type": "node", "id": 798568111, "lat": 37.5560427, "lon": 126.8687235}, {"type": "node", "id": 798568112, "lat": 37.556079, "lon": 126.8690133, "tags": {"direction": "both", "traffic_calming": "hump"}}, {"type": "node", "id": 798568114, "lat": 37.5550942, "lon": 126.8657476}, {"type": "node", "id": 798572250, "lat": 37.5603519, "lon": 126.890755}, {"type": "node", "id": 930164455, "lat": 37.5709642, "lon": 126.8722657}, {"type": "node", "id": 930164457, "lat": 37.5635619, "lon": 126.8851155}, {"type": "node", "id": 930164469, "lat": 37.5672924, "lon": 126.8786497}, {"type": "node", "id": 1115265948, "lat": 37.5754607, "lon": 126.8655504}, {"type": "node", "id": 1133534447, "lat": 37.5676193, "lon": 126.8789727}, {"type": "node", "id": 1133534448, "lat": 37.5688952, "lon": 126.8801486}, {"type": "node", "id": 1133534451, "lat": 37.5690203, "lon": 126.8760332}, {"type": "node", "id": 1133534456, "lat": 37.5690049, "lon": 126.8800018}, {"type": "node", "id": 1133534459, "lat": 37.5678534, "lon": 126.8789097}, {"type": "node", "id": 1133534460, "lat": 37.567641, "lon": 126.8790437}, {"type": "node", "id": 1133534461, "lat": 37.5675008, "lon": 126.8789797}, {"type": "node", "id": 1133534463, "lat": 37.5676826, "lon": 126.8788338}, {"type": "node", "id": 1133534466, "lat": 37.5677482, "lon": 126.8788397}, {"type": "node", "id": 1133534469, "lat": 37.5677545, "lon": 126.8787526}, {"type": "node", "id": 1133534471, "lat": 37.5677413, "lon": 126.8785456}, {"type": "node", "id": 1133534473, "lat": 37.5662495, "lon": 126.8808407}, {"type": "node", "id": 1133534480, "lat": 37.5676334, "lon": 126.8788752}, {"type": "node", "id": 1994676496, "lat": 37.5564933, "lon": 126.8630716}, {"type": "node", "id": 2139867172, "lat": 37.5602282, "lon": 126.8909651, "tags": {"highway": "motorway_junction", "name": "\uc131\uc0b0\ub300\uad50 \ubd81\ub2e8", "ref": "8B"}}, {"type": "node", "id": 2141595929, "lat": 37.5751674, "lon": 126.8662254}, {"type": "node", "id": 2141595940, "lat": 37.5748528, "lon": 126.8665472}, {"type": "node", "id": 2141595943, "lat": 37.5738867, "lon": 126.8660964}, {"type": "node", "id": 2141595945, "lat": 37.5740619, "lon": 126.8642348}, {"type": "node", "id": 2141595950, "lat": 37.5731441, "lon": 126.8680035}, {"type": "node", "id": 2141595958, "lat": 37.5735156, "lon": 126.8678883}, {"type": "node", "id": 2141595960, "lat": 37.5734455, "lon": 126.8675799}, {"type": "node", "id": 2141595962, "lat": 37.5740238, "lon": 126.8653254}, {"type": "node", "id": 2141595982, "lat": 37.5734816, "lon": 126.8672875}, {"type": "node", "id": 2141595985, "lat": 37.5608012, "lon": 126.8903536}, {"type": "node", "id": 2141595986, "lat": 37.5752163, "lon": 126.8634788}, {"type": "node", "id": 2141595987, "lat": 37.5735029, "lon": 126.8669442}, {"type": "node", "id": 2141595999, "lat": 37.5739471, "lon": 126.8665677}, {"type": "node", "id": 2141596006, "lat": 37.5734345, "lon": 126.8684717, "tags": {"highway": "motorway_junction", "name": "\uac00\uc591\ub300\uad50 \ubd81\ub2e8", "ref": "6"}}, {"type": "node", "id": 2141596008, "lat": 37.5731339, "lon": 126.8680292}, {"type": "node", "id": 2141596010, "lat": 37.5742872, "lon": 126.864209}, {"type": "node", "id": 2141596013, "lat": 37.5740726, "lon": 126.8680412}, {"type": "node", "id": 2141596014, "lat": 37.5746997, "lon": 126.8640796}, {"type": "node", "id": 2141596015, "lat": 37.5745397, "lon": 126.8641513}, {"type": "node", "id": 2141596018, "lat": 37.5737261, "lon": 126.8668745}, {"type": "node", "id": 2141596020, "lat": 37.5750306, "lon": 126.8646053}, {"type": "node", "id": 2141596028, "lat": 37.5748932, "lon": 126.8638543}, {"type": "node", "id": 2141596032, "lat": 37.57462, "lon": 126.8666369}, {"type": "node", "id": 2141596036, "lat": 37.5744235, "lon": 126.8668035}, {"type": "node", "id": 2141596037, "lat": 37.5739387, "lon": 126.8681056}, {"type": "node", "id": 2141596039, "lat": 37.5726528, "lon": 126.8692705}, {"type": "node", "id": 2141596041, "lat": 37.5741789, "lon": 126.8679339}, {"type": "node", "id": 2141596043, "lat": 37.5740285, "lon": 126.8666881}, {"type": "node", "id": 2141596044, "lat": 37.5738746, "lon": 126.8662747}, {"type": "node", "id": 2141596045, "lat": 37.575072, "lon": 126.866328}, {"type": "node", "id": 2141596049, "lat": 37.5747273, "lon": 126.8667645}, {"type": "node", "id": 2141596051, "lat": 37.5734518, "lon": 126.8673975}, {"type": "node", "id": 2141596054, "lat": 37.5734772, "lon": 126.8640347}, {"type": "node", "id": 2141596057, "lat": 37.5740011, "lon": 126.8649}, {"type": "node", "id": 2141596062, "lat": 37.5741517, "lon": 126.8667723}, {"type": "node", "id": 2141596063, "lat": 37.5737877, "lon": 126.8680922}, {"type": "node", "id": 2141596065, "lat": 37.562867, "lon": 126.8867348}, {"type": "node", "id": 2141596068, "lat": 37.575123, "lon": 126.864395}, {"type": "node", "id": 2141596070, "lat": 37.575117, "lon": 126.8655823}, {"type": "node", "id": 2141596076, "lat": 37.5740243, "lon": 126.8663536}, {"type": "node", "id": 2141596080, "lat": 37.5747838, "lon": 126.8655591}, {"type": "node", "id": 2141596083, "lat": 37.573463, "lon": 126.8677192}, {"type": "node", "id": 2141596088, "lat": 37.5736437, "lon": 126.8680035}, {"type": "node", "id": 2141596089, "lat": 37.5742729, "lon": 126.8659195}, {"type": "node", "id": 2141596090, "lat": 37.5739307, "lon": 126.8646807}, {"type": "node", "id": 2141596091, "lat": 37.5742405, "lon": 126.8674994}, {"type": "node", "id": 2141616414, "lat": 37.5641912, "lon": 126.8599622}, {"type": "node", "id": 2141616415, "lat": 37.5658071, "lon": 126.8575483}, {"type": "node", "id": 2141616418, "lat": 37.5648854, "lon": 126.8610971}, {"type": "node", "id": 2141616422, "lat": 37.5651381, "lon": 126.8606489}, {"type": "node", "id": 2141616423, "lat": 37.5649259, "lon": 126.8608429}, {"type": "node", "id": 2141616424, "lat": 37.5647541, "lon": 126.8608728}, {"type": "node", "id": 2141616428, "lat": 37.5644002, "lon": 126.8593069}, {"type": "node", "id": 2141616430, "lat": 37.5642357, "lon": 126.8577452}, {"type": "node", "id": 2141616440, "lat": 37.564002, "lon": 126.8619284}, {"type": "node", "id": 2141616444, "lat": 37.5653611, "lon": 126.8604534}, {"type": "node", "id": 2141616445, "lat": 37.5642225, "lon": 126.8606875}, {"type": "node", "id": 2141616451, "lat": 37.5663428, "lon": 126.8579882}, {"type": "node", "id": 2141616456, "lat": 37.5634386, "lon": 126.8568148}, {"type": "node", "id": 2141616459, "lat": 37.5676464, "lon": 126.8550765}, {"type": "node", "id": 2141616461, "lat": 37.564162, "lon": 126.8575811}, {"type": "node", "id": 2141616462, "lat": 37.5634993, "lon": 126.8627473}, {"type": "node", "id": 2141616464, "lat": 37.5593177, "lon": 126.8657932}, {"type": "node", "id": 2141616465, "lat": 37.5638085, "lon": 126.8613856}, {"type": "node", "id": 2141616466, "lat": 37.563917, "lon": 126.8572081}, {"type": "node", "id": 2141616468, "lat": 37.5687235, "lon": 126.8491563}, {"type": "node", "id": 2141616475, "lat": 37.5656623, "lon": 126.860026}, {"type": "node", "id": 2141616476, "lat": 37.5688328, "lon": 126.8534011}, {"type": "node", "id": 2141616479, "lat": 37.5665278, "lon": 126.8575322}, {"type": "node", "id": 2141616482, "lat": 37.56417, "lon": 126.8593238}, {"type": "node", "id": 2141616484, "lat": 37.5656256, "lon": 126.8598097}, {"type": "node", "id": 2141616486, "lat": 37.5644336, "lon": 126.8614965}, {"type": "node", "id": 2141616488, "lat": 37.5659958, "lon": 126.8591263}, {"type": "node", "id": 2141616489, "lat": 37.5625656, "lon": 126.8626536}, {"type": "node", "id": 2141616490, "lat": 37.56923, "lon": 126.8481406}, {"type": "node", "id": 2141616492, "lat": 37.5640807, "lon": 126.8580095, "tags": {"highway": "turning_circle"}}, {"type": "node", "id": 2141616494, "lat": 37.5600622, "lon": 126.8675958}, {"type": "node", "id": 2141616495, "lat": 37.5644866, "lon": 126.8607137}, {"type": "node", "id": 2141616496, "lat": 37.5643831, "lon": 126.8604823}, {"type": "node", "id": 2141616497, "lat": 37.5643361, "lon": 126.859994}, {"type": "node", "id": 2141616498, "lat": 37.5641296, "lon": 126.8607321}, {"type": "node", "id": 2141616507, "lat": 37.5598326, "lon": 126.8674134}, {"type": "node", "id": 2141616508, "lat": 37.5659691, "lon": 126.85858}, {"type": "node", "id": 2141616509, "lat": 37.5661217, "lon": 126.8582672}, {"type": "node", "id": 2141616510, "lat": 37.5645102, "lon": 126.8599198}, {"type": "node", "id": 2141616514, "lat": 37.5629678, "lon": 126.8631282}, {"type": "node", "id": 2141616516, "lat": 37.566228, "lon": 126.8584365}, {"type": "node", "id": 2141616517, "lat": 37.5647249, "lon": 126.8594263}, {"type": "node", "id": 2141616519, "lat": 37.5643811, "lon": 126.8596601}, {"type": "node", "id": 2141616520, "lat": 37.5630811, "lon": 126.863257}, {"type": "node", "id": 2141616522, "lat": 37.5645621, "lon": 126.8607937}, {"type": "node", "id": 2141616525, "lat": 37.564364, "lon": 126.8603495}, {"type": "node", "id": 2141616526, "lat": 37.5644111, "lon": 126.8600315}, {"type": "node", "id": 2141616532, "lat": 37.5659153, "lon": 126.8597717}, {"type": "node", "id": 2141616535, "lat": 37.5644631, "lon": 126.8594644}, {"type": "node", "id": 2141616538, "lat": 37.5602111, "lon": 126.8675528}, {"type": "node", "id": 2141616539, "lat": 37.5613517, "lon": 126.8659132}, {"type": "node", "id": 2141616540, "lat": 37.5599219, "lon": 126.8675582}, {"type": "node", "id": 2141616542, "lat": 37.5650566, "lon": 126.8601125}, {"type": "node", "id": 2141616543, "lat": 37.5673483, "lon": 126.8595211}, {"type": "node", "id": 2141616545, "lat": 37.5616803, "lon": 126.8641094}, {"type": "node", "id": 2141616546, "lat": 37.5602043, "lon": 126.8627913}, {"type": "node", "id": 2142060299, "lat": 37.574834, "lon": 126.8427469}, {"type": "node", "id": 2142060300, "lat": 37.5733879, "lon": 126.845212}, {"type": "node", "id": 2142060310, "lat": 37.5725384, "lon": 126.8470022}, {"type": "node", "id": 2142722910, "lat": 37.5618583, "lon": 126.8597194}, {"type": "node", "id": 2142722932, "lat": 37.5626145, "lon": 126.8583265}, {"type": "node", "id": 2142722963, "lat": 37.5634657, "lon": 126.8611633}, {"type": "node", "id": 2164945429, "lat": 37.569922, "lon": 126.8741067}, {"type": "node", "id": 2289016483, "lat": 37.5514908, "lon": 126.8639569, "tags": {"junction": "yes", "name": "\ub4f1\ucd0c\uc5ed", "name:ko": "\ub4f1\ucd0c\uc5ed"}}, {"type": "node", "id": 2456433663, "lat": 37.5541765, "lon": 126.8673213}, {"type": "node", "id": 2690921890, "lat": 37.5834403, "lon": 126.8218619}, {"type": "node", "id": 2690921895, "lat": 37.585991, "lon": 126.8166801}, {"type": "node", "id": 2825869578, "lat": 37.5572426, "lon": 126.8659113}, {"type": "node", "id": 2825869580, "lat": 37.5560944, "lon": 126.8667643}, {"type": "node", "id": 2825869581, "lat": 37.5578932, "lon": 126.8657719}, {"type": "node", "id": 2825869582, "lat": 37.5568939, "lon": 126.8671934}, {"type": "node", "id": 2825869583, "lat": 37.5558419, "lon": 126.8654298}, {"type": "node", "id": 2825869584, "lat": 37.5567705, "lon": 126.8673061}, {"type": "node", "id": 2825869585, "lat": 37.5576374, "lon": 126.8670234}, {"type": "node", "id": 2825869586, "lat": 37.5575226, "lon": 126.8661275}, {"type": "node", "id": 2825869587, "lat": 37.5577316, "lon": 126.8658523}, {"type": "node", "id": 2825869588, "lat": 37.5576593, "lon": 126.8663566}, {"type": "node", "id": 2825869589, "lat": 37.5587473, "lon": 126.8655482}, {"type": "node", "id": 2825869590, "lat": 37.5555253, "lon": 126.8660325}, {"type": "node", "id": 2825869592, "lat": 37.5570555, "lon": 126.8671291}, {"type": "node", "id": 2825869593, "lat": 37.5581611, "lon": 126.8655948}, {"type": "node", "id": 2825869594, "lat": 37.5576763, "lon": 126.866952}, {"type": "node", "id": 2825869595, "lat": 37.5557286, "lon": 126.8676816}, {"type": "node", "id": 2825869596, "lat": 37.5578039, "lon": 126.866539}, {"type": "node", "id": 2825869597, "lat": 37.5573568, "lon": 126.8659398}, {"type": "node", "id": 2825869598, "lat": 37.5565062, "lon": 126.867769}, {"type": "node", "id": 2825869599, "lat": 37.5575524, "lon": 126.8670609}, {"type": "node", "id": 2825869600, "lat": 37.5564601, "lon": 126.867805}, {"type": "node", "id": 2825869601, "lat": 37.5584758, "lon": 126.8654983}, {"type": "node", "id": 2825869602, "lat": 37.5552356, "lon": 126.8633006}, {"type": "node", "id": 2825869603, "lat": 37.5559151, "lon": 126.867651}, {"type": "node", "id": 2825869604, "lat": 37.5556393, "lon": 126.8676387}, {"type": "node", "id": 2825869605, "lat": 37.5569995, "lon": 126.8657413}, {"type": "node", "id": 2825869606, "lat": 37.5560093, "lon": 126.8655251}, {"type": "node", "id": 2825950890, "lat": 37.5673947, "lon": 126.8508078}, {"type": "node", "id": 2858504972, "lat": 37.5660411, "lon": 126.8808038}, {"type": "node", "id": 2938354331, "lat": 37.5737494, "lon": 126.8642369}, {"type": "node", "id": 3031379400, "lat": 37.5563631, "lon": 126.8729847}, {"type": "node", "id": 3031379401, "lat": 37.5591149, "lon": 126.8654291}, {"type": "node", "id": 3031379402, "lat": 37.559544, "lon": 126.8666366}, {"type": "node", "id": 3031379403, "lat": 37.5595466, "lon": 126.8687288}, {"type": "node", "id": 3031379404, "lat": 37.5608991, "lon": 126.8664646}, {"type": "node", "id": 3031379405, "lat": 37.5630616, "lon": 126.8627312}, {"type": "node", "id": 3031379406, "lat": 37.5632907, "lon": 126.8630959}, {"type": "node", "id": 3031379407, "lat": 37.5635852, "lon": 126.8626945}, {"type": "node", "id": 3031379409, "lat": 37.5639434, "lon": 126.8612288}, {"type": "node", "id": 3031379410, "lat": 37.5639871, "lon": 126.8610568}, {"type": "node", "id": 3031379411, "lat": 37.5642652, "lon": 126.8579212}, {"type": "node", "id": 3031379413, "lat": 37.5643094, "lon": 126.8582242}, {"type": "node", "id": 3031379422, "lat": 37.5658457, "lon": 126.8598627}, {"type": "node", "id": 3042643176, "lat": 37.5581107, "lon": 126.8606401}, {"type": "node", "id": 3042643876, "lat": 37.5576963, "lon": 126.8614217}, {"type": "node", "id": 3042644553, "lat": 37.5558211, "lon": 126.8632035}, {"type": "node", "id": 3042645651, "lat": 37.5580679, "lon": 126.8607184}, {"type": "node", "id": 3042645657, "lat": 37.5577612, "lon": 126.863924}, {"type": "node", "id": 3347412393, "lat": 37.569593, "lon": 126.8806547, "tags": {"junction": "yes", "name": "\ub178\uc744\uacf5\uc6d0\uc785\uad6c\uad50\ucc28\ub85c"}}, {"type": "node", "id": 3414087347, "lat": 37.567902, "lon": 126.8789605}, {"type": "node", "id": 3414087349, "lat": 37.570391, "lon": 126.8792525}, {"type": "node", "id": 3414087352, "lat": 37.570909, "lon": 126.8792525}, {"type": "node", "id": 3414087367, "lat": 37.5721335, "lon": 126.8716947}, {"type": "node", "id": 3414087369, "lat": 37.5723542, "lon": 126.8801848}, {"type": "node", "id": 3414087375, "lat": 37.5730677, "lon": 126.8804956}, {"type": "node", "id": 3414087382, "lat": 37.5732778, "lon": 126.8805184}, {"type": "node", "id": 3414087387, "lat": 37.5734951, "lon": 126.8803859}, {"type": "node", "id": 3414087389, "lat": 37.5737124, "lon": 126.883321}, {"type": "node", "id": 3414087798, "lat": 37.5742261, "lon": 126.8795}, {"type": "node", "id": 3414087812, "lat": 37.5746903, "lon": 126.8789372}, {"type": "node", "id": 3414087822, "lat": 37.575201, "lon": 126.8666487}, {"type": "node", "id": 3414087827, "lat": 37.5753278, "lon": 126.8665391}, {"type": "node", "id": 3414087833, "lat": 37.5755741, "lon": 126.8665985}, {"type": "node", "id": 3414087837, "lat": 37.5758892, "lon": 126.8667264}, {"type": "node", "id": 3414087848, "lat": 37.5761789, "lon": 126.8674987}, {"type": "node", "id": 3414087851, "lat": 37.5766389, "lon": 126.8685681}, {"type": "node", "id": 3414087854, "lat": 37.5768526, "lon": 126.8695049}, {"type": "node", "id": 3414087855, "lat": 37.576983, "lon": 126.8706703}, {"type": "node", "id": 3414087857, "lat": 37.5771351, "lon": 126.87301}, {"type": "node", "id": 3414087859, "lat": 37.5773307, "lon": 126.8754184}, {"type": "node", "id": 3414087860, "lat": 37.5773669, "lon": 126.8749614}, {"type": "node", "id": 3414087861, "lat": 37.5773923, "lon": 126.8752676}, {"type": "node", "id": 3464447066, "lat": 37.570914, "lon": 126.8818106}, {"type": "node", "id": 3464447067, "lat": 37.5710273, "lon": 126.8827252}, {"type": "node", "id": 3638110426, "lat": 37.5681583, "lon": 126.8785168}, {"type": "node", "id": 3643726804, "lat": 37.5679205, "lon": 126.8789284}, {"type": "node", "id": 3849185769, "lat": 37.5677765, "lon": 126.8791777}, {"type": "node", "id": 4604992808, "lat": 37.5706433, "lon": 126.8429835}, {"type": "node", "id": 4604992810, "lat": 37.5704566, "lon": 126.8436756}, {"type": "node", "id": 4605022120, "lat": 37.5568502, "lon": 126.8631112}, {"type": "node", "id": 4605024545, "lat": 37.558918, "lon": 126.8613814}, {"type": "node", "id": 4605033164, "lat": 37.5570393, "lon": 126.8657691}, {"type": "node", "id": 4605033165, "lat": 37.5568384, "lon": 126.8653583}, {"type": "node", "id": 4605033166, "lat": 37.556697, "lon": 126.8649971}, {"type": "node", "id": 4605033167, "lat": 37.5565308, "lon": 126.8646136}, {"type": "node", "id": 4605033168, "lat": 37.5562029, "lon": 126.8643015}, {"type": "node", "id": 4605038131, "lat": 37.5548837, "lon": 126.8720613}, {"type": "node", "id": 4605038143, "lat": 37.5543114, "lon": 126.8696762}, {"type": "node", "id": 4605038144, "lat": 37.5555011, "lon": 126.8710704}, {"type": "node", "id": 4605038145, "lat": 37.5563839, "lon": 126.8718994}, {"type": "node", "id": 4605038146, "lat": 37.556143, "lon": 126.8699448}, {"type": "node", "id": 4605038147, "lat": 37.5566056, "lon": 126.8704252}, {"type": "node", "id": 4605038148, "lat": 37.55677, "lon": 126.8705701}, {"type": "node", "id": 4605038149, "lat": 37.5569661, "lon": 126.8710428}, {"type": "node", "id": 4605038150, "lat": 37.5569732, "lon": 126.8712211}, {"type": "node", "id": 4605038151, "lat": 37.5565791, "lon": 126.8716849}, {"type": "node", "id": 4631542219, "lat": 37.5644344, "lon": 126.855011}, {"type": "node", "id": 4634202874, "lat": 37.5619976, "lon": 126.8594619}, {"type": "node", "id": 4636764537, "lat": 37.5690926, "lon": 126.8484843}, {"type": "node", "id": 4636808759, "lat": 37.566913, "lon": 126.851368}, {"type": "node", "id": 4636902640, "lat": 37.5700494, "lon": 126.8451851}, {"type": "node", "id": 4639333447, "lat": 37.5600423, "lon": 126.8627743}, {"type": "node", "id": 4639333448, "lat": 37.5594381, "lon": 126.8622082}, {"type": "node", "id": 4639333449, "lat": 37.5593165, "lon": 126.8616728}, {"type": "node", "id": 4639333450, "lat": 37.5601577, "lon": 126.8628795}, {"type": "node", "id": 4656832307, "lat": 37.5596494, "lon": 126.8624249}, {"type": "node", "id": 4656832311, "lat": 37.5594834, "lon": 126.8622773}, {"type": "node", "id": 4656832325, "lat": 37.5598116, "lon": 126.8625691}, {"type": "node", "id": 4656832326, "lat": 37.5595286, "lon": 126.8623175}, {"type": "node", "id": 4681899725, "lat": 37.5731811, "lon": 126.8638161}, {"type": "node", "id": 4681926739, "lat": 37.5691678, "lon": 126.8856714}, {"type": "node", "id": 4681957524, "lat": 37.5687231, "lon": 126.8867432}, {"type": "node", "id": 4681957525, "lat": 37.5665799, "lon": 126.8848997}, {"type": "node", "id": 4681957526, "lat": 37.5667956, "lon": 126.8845413}, {"type": "node", "id": 4681969841, "lat": 37.5700883, "lon": 126.8798239}, {"type": "node", "id": 4682031226, "lat": 37.57676, "lon": 126.8801}, {"type": "node", "id": 4684562292, "lat": 37.5616764, "lon": 126.8883404}, {"type": "node", "id": 4684562293, "lat": 37.562229, "lon": 126.8874132}, {"type": "node", "id": 4684562294, "lat": 37.5625464, "lon": 126.8868661, "tags": {"highway": "motorway_junction", "name": "\uc131\uc0b0\ub300\uad50\ubd84\uae30\uc810", "ref": "8A"}}, {"type": "node", "id": 4684562299, "lat": 37.5623381, "lon": 126.8872251}, {"type": "node", "id": 4684562301, "lat": 37.5626063, "lon": 126.8867628}, {"type": "node", "id": 4684562310, "lat": 37.561018, "lon": 126.8895344}, {"type": "node", "id": 4688584727, "lat": 37.571677, "lon": 126.8834282}, {"type": "node", "id": 4688584728, "lat": 37.5717158, "lon": 126.8837074}, {"type": "node", "id": 4688584729, "lat": 37.5702699, "lon": 126.8815876}, {"type": "node", "id": 4688584730, "lat": 37.5699719, "lon": 126.8809823}, {"type": "node", "id": 4688584731, "lat": 37.5716752, "lon": 126.8838312}, {"type": "node", "id": 4688584732, "lat": 37.5717182, "lon": 126.8835433}, {"type": "node", "id": 4694620253, "lat": 37.5642199, "lon": 126.8617218}, {"type": "node", "id": 4694620254, "lat": 37.5641243, "lon": 126.8618531}, {"type": "node", "id": 4694620255, "lat": 37.5643114, "lon": 126.8616147}, {"type": "node", "id": 4694620256, "lat": 37.5641721, "lon": 126.8617874}, {"type": "node", "id": 4694620257, "lat": 37.5645575, "lon": 126.8613976}, {"type": "node", "id": 4694620258, "lat": 37.5647199, "lon": 126.8612623}, {"type": "node", "id": 4694620259, "lat": 37.5650097, "lon": 126.8609536}, {"type": "node", "id": 4694620260, "lat": 37.5651508, "lon": 126.860771}, {"type": "node", "id": 4694620261, "lat": 37.5655611, "lon": 126.8601533}, {"type": "node", "id": 4694620262, "lat": 37.565084, "lon": 126.8607265}, {"type": "node", "id": 4694620263, "lat": 37.5650149, "lon": 126.8607918}, {"type": "node", "id": 4694620264, "lat": 37.5648427, "lon": 126.8608667}, {"type": "node", "id": 4694620265, "lat": 37.5646558, "lon": 126.8608484}, {"type": "node", "id": 4694620266, "lat": 37.5644197, "lon": 126.8606003}, {"type": "node", "id": 4694620267, "lat": 37.5643786, "lon": 126.8602078}, {"type": "node", "id": 4694620268, "lat": 37.5644456, "lon": 126.8597698}, {"type": "node", "id": 4694620269, "lat": 37.5660963, "lon": 126.8588649}, {"type": "node", "id": 4694620270, "lat": 37.5658426, "lon": 126.8594292}, {"type": "node", "id": 4694620271, "lat": 37.5638172, "lon": 126.8571026}, {"type": "node", "id": 4694620272, "lat": 37.56404, "lon": 126.8573716}, {"type": "node", "id": 4694620273, "lat": 37.5643451, "lon": 126.8585495}, {"type": "node", "id": 4694620274, "lat": 37.5643832, "lon": 126.8589424}, {"type": "node", "id": 4694620275, "lat": 37.5642618, "lon": 126.8603207}, {"type": "node", "id": 4694620276, "lat": 37.5640975, "lon": 126.8609439}, {"type": "node", "id": 4694620277, "lat": 37.564332, "lon": 126.8604118}, {"type": "node", "id": 4694620278, "lat": 37.5649207, "lon": 126.8590598}, {"type": "node", "id": 4695045503, "lat": 37.5741704, "lon": 126.8675667}, {"type": "node", "id": 4695045506, "lat": 37.574078, "lon": 126.8676954}, {"type": "node", "id": 4695045507, "lat": 37.5746972, "lon": 126.8665073}, {"type": "node", "id": 4695045508, "lat": 37.5745355, "lon": 126.8667425}, {"type": "node", "id": 4695045509, "lat": 37.5742865, "lon": 126.8668166}, {"type": "node", "id": 4695045510, "lat": 37.5738986, "lon": 126.8664243}, {"type": "node", "id": 4695045513, "lat": 37.575039, "lon": 126.8659187}, {"type": "node", "id": 4695045515, "lat": 37.5743354, "lon": 126.867639}, {"type": "node", "id": 4695045517, "lat": 37.5752372, "lon": 126.8661817}, {"type": "node", "id": 4695045537, "lat": 37.5752023, "lon": 126.8641582}, {"type": "node", "id": 4695045538, "lat": 37.5754079, "lon": 126.8632409}, {"type": "node", "id": 4696904531, "lat": 37.5738668, "lon": 126.8658335}, {"type": "node", "id": 4696904532, "lat": 37.5740254, "lon": 126.8651286}, {"type": "node", "id": 4696904533, "lat": 37.574008, "lon": 126.8654987}, {"type": "node", "id": 4696904534, "lat": 37.5737971, "lon": 126.8644403}, {"type": "node", "id": 4739847042, "lat": 37.5751481, "lon": 126.8649275}, {"type": "node", "id": 4739847044, "lat": 37.5752659, "lon": 126.8653345}, {"type": "node", "id": 4739847045, "lat": 37.5749687, "lon": 126.8651751}, {"type": "node", "id": 4871097568, "lat": 37.5908316, "lon": 126.806045}, {"type": "node", "id": 5062482487, "lat": 37.5693693, "lon": 126.8476907}, {"type": "node", "id": 5093837168, "lat": 37.5676202, "lon": 126.8505903}, {"type": "node", "id": 5294397120, "lat": 37.5707476, "lon": 126.873091}, {"type": "node", "id": 5294398221, "lat": 37.5714866, "lon": 126.8720705}, {"type": "node", "id": 5294398222, "lat": 37.5717959, "lon": 126.8715867}, {"type": "node", "id": 5294398223, "lat": 37.5718926, "lon": 126.8713713}, {"type": "node", "id": 5294398224, "lat": 37.5718829, "lon": 126.8712778}, {"type": "node", "id": 5294398225, "lat": 37.5717637, "lon": 126.8711192}, {"type": "node", "id": 5294398226, "lat": 37.5714866, "lon": 126.8708956}, {"type": "node", "id": 5294398227, "lat": 37.5714028, "lon": 126.8708753}, {"type": "node", "id": 5294398228, "lat": 37.571348, "lon": 126.8708915}, {"type": "node", "id": 5294398229, "lat": 37.5712417, "lon": 126.8710298}, {"type": "node", "id": 5294398230, "lat": 37.5711128, "lon": 126.8714038}, {"type": "node", "id": 5294398231, "lat": 37.5708614, "lon": 126.8720787}, {"type": "node", "id": 5294398232, "lat": 37.5707018, "lon": 126.8727293}, {"type": "node", "id": 5356262108, "lat": 37.5642001, "lon": 126.8554356}, {"type": "node", "id": 5370459333, "lat": 37.5634542, "lon": 126.8853012}, {"type": "node", "id": 5703054986, "lat": 37.5642547, "lon": 126.8839841, "tags": {"highway": "motorway_junction", "name": "\ud55c\uac15\uacf5\uc6d0\uc785\uad6c", "ref": "H-2"}}, {"type": "node", "id": 5703054993, "lat": 37.5683192, "lon": 126.8760728}, {"type": "node", "id": 5703054994, "lat": 37.5682597, "lon": 126.8764313}, {"type": "node", "id": 5703054995, "lat": 37.5681004, "lon": 126.8770307}, {"type": "node", "id": 5703054996, "lat": 37.5679614, "lon": 126.877494}, {"type": "node", "id": 5703055020, "lat": 37.5700978, "lon": 126.8737962}, {"type": "node", "id": 5703055121, "lat": 37.5697354, "lon": 126.8740856}, {"type": "node", "id": 5703055122, "lat": 37.5694786, "lon": 126.8742954}, {"type": "node", "id": 5836270443, "lat": 37.5650635, "lon": 126.853871, "tags": {"crossing": "zebra", "highway": "crossing"}}, {"type": "node", "id": 5836270447, "lat": 37.5652368, "lon": 126.8535763, "tags": {"crossing": "zebra", "highway": "crossing"}}, {"type": "node", "id": 5842903328, "lat": 37.5862935, "lon": 126.8157962}, {"type": "node", "id": 5983520731, "lat": 37.5625751, "lon": 126.8583988}, {"type": "node", "id": 5983520736, "lat": 37.5619809, "lon": 126.8598295}, {"type": "node", "id": 5983520745, "lat": 37.5640142, "lon": 126.8602553}, {"type": "node", "id": 5983520748, "lat": 37.5638953, "lon": 126.8604521}, {"type": "node", "id": 5983520751, "lat": 37.5637582, "lon": 126.860679}, {"type": "node", "id": 5983520754, "lat": 37.5636436, "lon": 126.8608687}, {"type": "node", "id": 6706464983, "lat": 37.5739779, "lon": 126.8642354}, {"type": "node", "id": 6706474612, "lat": 37.56368, "lon": 126.8563765}, {"type": "node", "id": 6706474614, "lat": 37.5635714, "lon": 126.8569157, "tags": {"crossing": "traffic_signals", "crossing:markings": "zebra:double", "highway": "crossing"}}, {"type": "node", "id": 6706474635, "lat": 37.5738581, "lon": 126.8645501}, {"type": "node", "id": 7122163081, "lat": 37.5808575, "lon": 126.8280063}, {"type": "node", "id": 7160386054, "lat": 37.5597456, "lon": 126.8671793}, {"type": "node", "id": 7366088086, "lat": 37.560483, "lon": 126.8908961}, {"type": "node", "id": 7495737013, "lat": 37.5702563, "lon": 126.8444182}, {"type": "node", "id": 7617101083, "lat": 37.5554843, "lon": 126.8677653, "tags": {"traffic_calming": "hump"}}, {"type": "node", "id": 7617101084, "lat": 37.5555436, "lon": 126.8676707}, {"type": "node", "id": 7980080033, "lat": 37.5560455, "lon": 126.8687947}, {"type": "node", "id": 8154128188, "lat": 37.5584172, "lon": 126.8600621}, {"type": "node", "id": 8269969202, "lat": 37.5740623, "lon": 126.8443881, "tags": {"direction": "125", "highway": "speed_camera", "maxspeed": "80"}}, {"type": "node", "id": 8434002967, "lat": 37.556322, "lon": 126.867766}, {"type": "node", "id": 8436561094, "lat": 37.5564911, "lon": 126.8703063}, {"type": "node", "id": 8436561097, "lat": 37.5562386, "lon": 126.8700441}, {"type": "node", "id": 8453190653, "lat": 37.5653545, "lon": 126.8534028}, {"type": "node", "id": 8453207538, "lat": 37.5608533, "lon": 126.8615771}, {"type": "node", "id": 8453207560, "lat": 37.5616522, "lon": 126.8601004}, {"type": "node", "id": 8453295815, "lat": 37.5585695, "lon": 126.861098}, {"type": "node", "id": 8455940602, "lat": 37.5641484, "lon": 126.8588873}, {"type": "node", "id": 8455940603, "lat": 37.564174, "lon": 126.8594629}, {"type": "node", "id": 8455940609, "lat": 37.563347, "lon": 126.8610567}, {"type": "node", "id": 8455964935, "lat": 37.5596408, "lon": 126.8638567}, {"type": "node", "id": 8456478409, "lat": 37.5710905, "lon": 126.8819694}, {"type": "node", "id": 8456521433, "lat": 37.5687419, "lon": 126.8797209}, {"type": "node", "id": 8456521435, "lat": 37.5703688, "lon": 126.8792944}, {"type": "node", "id": 8456619716, "lat": 37.5556158, "lon": 126.8708507}, {"type": "node", "id": 8456622827, "lat": 37.5560361, "lon": 126.8701201}, {"type": "node", "id": 8457933628, "lat": 37.5574904, "lon": 126.8660893}, {"type": "node", "id": 8457933641, "lat": 37.5566873, "lon": 126.8674518}, {"type": "node", "id": 8458097648, "lat": 37.5689203, "lon": 126.8801666}, {"type": "node", "id": 8458097649, "lat": 37.5689503, "lon": 126.88015}, {"type": "node", "id": 8458097650, "lat": 37.5689747, "lon": 126.8801299}, {"type": "node", "id": 8458097651, "lat": 37.5689917, "lon": 126.8800937}, {"type": "node", "id": 8458097652, "lat": 37.5690055, "lon": 126.8800548}, {"type": "node", "id": 8458097653, "lat": 37.5691618, "lon": 126.8803404}, {"type": "node", "id": 8459523597, "lat": 37.5546776, "lon": 126.8676499}, {"type": "node", "id": 8459523608, "lat": 37.5545996, "lon": 126.8664479}, {"type": "node", "id": 8459541267, "lat": 37.5561295, "lon": 126.8691253}, {"type": "node", "id": 8537264160, "lat": 37.5595559, "lon": 126.8640171}, {"type": "node", "id": 8537264169, "lat": 37.5617926, "lon": 126.863931}, {"type": "node", "id": 8537264184, "lat": 37.5639667, "lon": 126.860334}, {"type": "node", "id": 8738613140, "lat": 37.5906033, "lon": 126.8064764}, {"type": "node", "id": 10102811253, "lat": 37.5669623, "lon": 126.888335}, {"type": "node", "id": 10102811254, "lat": 37.566775, "lon": 126.888263}, {"type": "node", "id": 10106987101, "lat": 37.5654848, "lon": 126.8867961}, {"type": "node", "id": 10109339008, "lat": 37.5691633, "lon": 126.8812648, "tags": {"highway": "crossing"}}, {"type": "node", "id": 10203676708, "lat": 37.568779, "lon": 126.8865094}, {"type": "node", "id": 10203723464, "lat": 37.5670659, "lon": 126.8861601}, {"type": "node", "id": 10203723465, "lat": 37.5665019, "lon": 126.8869768}, {"type": "node", "id": 10203723466, "lat": 37.5655892, "lon": 126.8871021}, {"type": "node", "id": 10203723467, "lat": 37.565893, "lon": 126.8859493}, {"type": "node", "id": 10203723468, "lat": 37.5656994, "lon": 126.8863282}, {"type": "node", "id": 10203723499, "lat": 37.5673197, "lon": 126.8857225}, {"type": "node", "id": 10203723501, "lat": 37.567378, "lon": 126.885622}, {"type": "node", "id": 10203723503, "lat": 37.5675982, "lon": 126.8853601}, {"type": "node", "id": 10203723524, "lat": 37.5681464, "lon": 126.8823164}, {"type": "node", "id": 10203723525, "lat": 37.5682915, "lon": 126.8842932}, {"type": "node", "id": 10203723526, "lat": 37.5680968, "lon": 126.8845785}, {"type": "node", "id": 10203723527, "lat": 37.5678763, "lon": 126.8850365}, {"type": "node", "id": 10203723559, "lat": 37.5676951, "lon": 126.8830506}, {"type": "node", "id": 10203723560, "lat": 37.5671301, "lon": 126.8839696}, {"type": "node", "id": 10203723579, "lat": 37.566896, "lon": 126.8843697}, {"type": "node", "id": 10203723638, "lat": 37.5672738, "lon": 126.8882089}, {"type": "node", "id": 10203723710, "lat": 37.5699415, "lon": 126.8842904}, {"type": "node", "id": 10203723711, "lat": 37.5683488, "lon": 126.8841872}, {"type": "node", "id": 10203723731, "lat": 37.5699178, "lon": 126.8833559}, {"type": "node", "id": 10203723736, "lat": 37.5697299, "lon": 126.8846681}, {"type": "node", "id": 10203723787, "lat": 37.5676283, "lon": 126.8880277}, {"type": "node", "id": 10203723788, "lat": 37.5679488, "lon": 126.8878532}, {"type": "node", "id": 10203723827, "lat": 37.5695463, "lon": 126.8849958}, {"type": "node", "id": 10203723832, "lat": 37.5690497, "lon": 126.8858995}, {"type": "node", "id": 10203723858, "lat": 37.5682431, "lon": 126.8877399}, {"type": "node", "id": 10203723869, "lat": 37.5684393, "lon": 126.8876478}, {"type": "node", "id": 10203723890, "lat": 37.5689122, "lon": 126.8862092}, {"type": "node", "id": 10203723902, "lat": 37.5658832, "lon": 126.8859685}, {"type": "node", "id": 10203723911, "lat": 37.5663802, "lon": 126.8852218}, {"type": "node", "id": 10203723919, "lat": 37.5665175, "lon": 126.8850066}, {"type": "node", "id": 10650909353, "lat": 37.5682999, "lon": 126.8497277}, {"type": "node", "id": 10669763546, "lat": 37.565779, "lon": 126.8527769}, {"type": "node", "id": 10669942889, "lat": 37.559747, "lon": 126.8625116}, {"type": "node", "id": 10672019558, "lat": 37.5594295, "lon": 126.8642562}, {"type": "node", "id": 10681207509, "lat": 37.5700324, "lon": 126.8452485}, {"type": "node", "id": 10681256655, "lat": 37.5571791, "lon": 126.8658669}, {"type": "node", "id": 10681256656, "lat": 37.5584288, "lon": 126.8655127}, {"type": "node", "id": 10681256709, "lat": 37.5565128, "lon": 126.8645968}, {"type": "node", "id": 10681256710, "lat": 37.5558982, "lon": 126.8654517}, {"type": "node", "id": 10682249085, "lat": 37.5567101, "lon": 126.8630479}, {"type": "node", "id": 10705895889, "lat": 37.5545462, "lon": 126.8675581}, {"type": "node", "id": 10814323658, "lat": 37.551937, "lon": 126.8639029}, {"type": "node", "id": 10814323659, "lat": 37.5522972, "lon": 126.8638328}, {"type": "node", "id": 10814323660, "lat": 37.5525838, "lon": 126.8637764}, {"type": "node", "id": 10814323661, "lat": 37.5529957, "lon": 126.8637055}, {"type": "node", "id": 10814323666, "lat": 37.553806, "lon": 126.8635399}, {"type": "node", "id": 10814323667, "lat": 37.5540383, "lon": 126.86349}, {"type": "node", "id": 10814323668, "lat": 37.5543419, "lon": 126.8634467}, {"type": "node", "id": 10814323669, "lat": 37.5549834, "lon": 126.8633435}, {"type": "node", "id": 10814323672, "lat": 37.5561791, "lon": 126.8631437}, {"type": "node", "id": 10814323674, "lat": 37.5562226, "lon": 126.8631258}, {"type": "node", "id": 10814323683, "lat": 37.5585832, "lon": 126.8597487}, {"type": "node", "id": 11187794345, "lat": 37.5634131, "lon": 126.8858249}, {"type": "node", "id": 11187794347, "lat": 37.5646305, "lon": 126.8837564}, {"type": "node", "id": 11582230904, "lat": 37.5561986, "lon": 126.8692755, "tags": {"direction": "both", "traffic_calming": "hump"}}, {"type": "node", "id": 11582230905, "lat": 37.55623, "lon": 126.8697588}, {"type": "node", "id": 11582230906, "lat": 37.5560766, "lon": 126.8700625}, {"type": "node", "id": 11582230907, "lat": 37.5556493, "lon": 126.8707991}, {"type": "node", "id": 11582230908, "lat": 37.5555563, "lon": 126.8709612}, {"type": "node", "id": 11582230909, "lat": 37.5551391, "lon": 126.8706569, "tags": {"traffic_calming": "hump"}}, {"type": "node", "id": 11582230910, "lat": 37.5548802, "lon": 126.8703686, "tags": {"traffic_calming": "hump"}}, {"type": "node", "id": 11582230924, "lat": 37.5556698, "lon": 126.8682949, "tags": {"direction": "both", "traffic_calming": "hump"}}, {"type": "node", "id": 11582230925, "lat": 37.5556523, "lon": 126.8674823, "tags": {"traffic_calming": "hump"}}, {"type": "node", "id": 11582230926, "lat": 37.5556986, "lon": 126.86767, "tags": {"traffic_calming": "hump"}}, {"type": "node", "id": 11582230927, "lat": 37.5550971, "lon": 126.8678951, "tags": {"direction": "both", "traffic_calming": "hump"}}, {"type": "node", "id": 11582230930, "lat": 37.5542851, "lon": 126.8673912, "tags": {"highway": "crossing"}}, {"type": "node", "id": 11582230933, "lat": 37.5542376, "lon": 126.8671815, "tags": {"highway": "crossing"}}, {"type": "node", "id": 11582230947, "lat": 37.5551965, "lon": 126.8658099, "tags": {"crossing": "uncontrolled", "highway": "crossing"}}, {"type": "node", "id": 11582230949, "lat": 37.5557996, "lon": 126.8654013}, {"type": "node", "id": 11582230951, "lat": 37.5556606, "lon": 126.8652671, "tags": {"crossing": "uncontrolled", "highway": "crossing"}}, {"type": "node", "id": 11582230954, "lat": 37.5562909, "lon": 126.8643853, "tags": {"crossing": "uncontrolled", "highway": "crossing"}}, {"type": "node", "id": 11582230957, "lat": 37.5546368, "lon": 126.8676172, "tags": {"traffic_calming": "hump"}}, {"type": "node", "id": 11582245871, "lat": 37.5551721, "lon": 126.8656507, "tags": {"highway": "crossing"}}, {"type": "node", "id": 11582245875, "lat": 37.5563308, "lon": 126.8644444}, {"type": "node", "id": 11582245876, "lat": 37.5588793, "lon": 126.8653155}, {"type": "node", "id": 11582245877, "lat": 37.5585553, "lon": 126.8655158}, {"type": "node", "id": 11582245883, "lat": 37.5567678, "lon": 126.8632627, "tags": {"highway": "crossing"}}, {"type": "node", "id": 11582245889, "lat": 37.5566876, "lon": 126.8630504, "tags": {"highway": "crossing"}}, {"type": "node", "id": 11582245892, "lat": 37.5569305, "lon": 126.8629509, "tags": {"highway": "crossing"}}, {"type": "node", "id": 11582245893, "lat": 37.5569699, "lon": 126.863218, "tags": {"crossing": "traffic_signals", "highway": "crossing"}}, {"type": "node", "id": 11582245944, "lat": 37.5555985, "lon": 126.8661267, "tags": {"traffic_calming": "hump"}}, {"type": "node", "id": 11582245945, "lat": 37.5559017, "lon": 126.8665165, "tags": {"traffic_calming": "hump"}}, {"type": "node", "id": 11582245947, "lat": 37.5559915, "lon": 126.8669314, "tags": {"traffic_calming": "hump"}}, {"type": "node", "id": 11582245954, "lat": 37.5582064, "lon": 126.8608232, "tags": {"highway": "crossing"}}, {"type": "node", "id": 11582245957, "lat": 37.557981, "lon": 126.860883, "tags": {"crossing": "traffic_signals", "highway": "crossing"}}, {"type": "node", "id": 11582245972, "lat": 37.5593994, "lon": 126.8583003}, {"type": "node", "id": 11582246026, "lat": 37.5555958, "lon": 126.8676437, "tags": {"highway": "crossing"}}, {"type": "node", "id": 11821418277, "lat": 37.5633734, "lon": 126.861316, "tags": {"crossing": "unmarked", "crossing:markings": "no", "highway": "crossing"}}, {"type": "node", "id": 11821418289, "lat": 37.5634012, "lon": 126.8568834, "tags": {"crossing": "traffic_signals", "crossing:markings": "zebra:double", "highway": "crossing"}}, {"type": "node", "id": 11821418309, "lat": 37.5619156, "lon": 126.8597708}, {"type": "node", "id": 11821418314, "lat": 37.5598028, "lon": 126.8673331}, {"type": "node", "id": 12147253736, "lat": 37.5665082, "lon": 126.8575806}, {"type": "node", "id": 12627978063, "lat": 37.555319, "lon": 126.8680524, "tags": {"crossing": "uncontrolled", "highway": "crossing"}}, {"type": "node", "id": 12627978065, "lat": 37.555356, "lon": 126.8679866, "tags": {"crossing": "uncontrolled", "highway": "crossing"}}, {"type": "node", "id": 12627978069, "lat": 37.5552616, "lon": 126.8680117, "tags": {"crossing": "uncontrolled", "highway": "crossing"}}, {"type": "node", "id": 12627978070, "lat": 37.555394, "lon": 126.8681043, "tags": {"crossing": "uncontrolled", "highway": "crossing"}}, {"type": "node", "id": 12627978071, "lat": 37.5555566, "lon": 126.8682167}, {"type": "node", "id": 12823414076, "lat": 37.5681258, "lon": 126.8785731}, {"type": "way", "id": 37398770, "nodes": [436873141, 10672019558, 8537264160, 8455964935, 4639333450, 2141616546, 436809431, 8453207538, 436868136, 8453207560, 2142722910, 4634202874, 436809433, 5983520731, 2142722932, 11821418289, 2141616456, 436809435, 6706474612, 436881126, 5356262108, 4631542219, 5836270443, 436847628, 5836270447, 8453190653, 10669763546, 436881128, 4636808759, 436881129, 436824835, 2825950890, 436881130, 5093837168, 10650909353, 436881131, 2141616468, 436881132, 436881133, 4636764537, 436881134, 2141616490, 5062482487, 436881135, 10681207509, 436881136, 4636902640, 7495737013, 4604992810, 4604992808, 436881137, 436881138], "tags": {"cycleway": "track", "highway": "secondary", "name": "\ud5c8\uc900\ub85c", "name:en": "Heojun-ro", "name:ko": "\ud5c8\uc900\ub85c", "segregated": "yes"}}, {"type": "way", "id": 37399652, "nodes": [436830207, 3347412393, 4688584730, 436830206, 3464447066, 8456478409, 436830203, 436830201, 436830200, 436830199, 3414087389, 436830198, 436830195, 436830193, 436830192, 436830190, 436830189, 436830188, 436830187, 4682031226, 436830183], "tags": {"cycleway:left": "track", "cycleway:right": "no", "highway": "tertiary", "name": "\ud558\ub298\uacf5\uc6d0\ub85c", "name:en": "Haneulgongwon-ro", "name:ko": "\ud558\ub298\uacf5\uc6d0\ub85c", "ncat": "\uad11\uc5ed\uc2dc\ub3c4\ub85c", "review": "no", "source": "NTIC"}}, {"type": "way", "id": 37402751, "nodes": [2289016483, 10814323658, 10814323659, 10814323660, 10814323661, 10814323666, 10814323667, 10814323668, 10814323669, 2825869602, 3042644553, 10814323672, 10814323674, 1994676496, 11582245889, 10682249085, 4605022120], "tags": {"highway": "secondary", "name": "\uacf5\ud56d\ub300\ub85c59\uae38", "name:en": "Gonghang-daero 59-gil", "name:ko": "\uacf5\ud56d\ub300\ub85c59\uae38", "review": "no", "source": "NTIC"}}, {"type": "way", "id": 37414925, "nodes": [436760154, 7366088086, 2141595985, 436760155, 2141596065, 11187794345, 436760156, 11187794347, 1133534473], "tags": {"bicycle": "no", "expressway": "yes", "foot": "no", "highway": "trunk", "horse": "no", "lanes": "5", "maxspeed": "80", "motor_vehicle": "yes", "name": "\uac15\ubcc0\ubd81\ub85c", "name:en": "Gangbyeonbuk-ro", "name:ko": "\uac15\ubcc0\ubd81\ub85c", "oneway": "yes", "ref": "23;77;70", "review": "no", "source": "NTIC", "surface": "asphalt", "toll": "no"}}, {"type": "way", "id": 38170453, "nodes": [449464861, 449464863, 449464865, 449464867, 449464869, 449464871, 449464873, 10109339008, 449464875, 449464877, 449464879, 449464881, 449464883, 449464885, 449464887, 449464888, 449464894, 449464896, 449464898, 449464900, 449464902, 449464904, 449464906, 449464908, 449464910, 449464912, 449464914, 449464916, 449464918], "tags": {"highway": "unclassified", "name": "\ud558\ub298\uacf5\uc6d0 \ud558\ub298\uc0ac\uba74\uae38", "name:ko": "\ud558\ub298\uacf5\uc6d0 \ud558\ub298\uc0ac\uba74\uae38"}}, {"type": "way", "id": 38170527, "nodes": [4688584730, 4688584729, 449464861, 3464447067, 4688584727, 4688584732, 4688584728, 4688584731, 449464939, 449471589, 449464938, 449464935, 449472640, 449472636, 449464931, 449464929, 449464927, 449464926, 449471230, 449464924, 449464922, 449464920, 449464918, 449468506, 449468508, 449468513, 449468515, 449468517, 449468519, 449468521, 449468523, 449468525, 449468527], "tags": {"cycleway:both": "lane", "highway": "unclassified", "name": "\ud558\ub298\uae38", "name:en": "Haneul-gil", "name:ko": "\ud558\ub298\uae38"}}, {"type": "way", "id": 38170561, "nodes": [4681957524, 10203676708, 10203723890, 10203723832, 449472537, 4681926739, 10203723827, 10203723736, 10203723710, 449472539, 449472540, 449472542, 449472543, 10203723731, 449473088, 449472545, 449472547, 449472548, 449472550, 10203723524, 10203723559, 10203723560, 10203723579, 4681957526, 449473568, 4681957525, 10203723919, 10203723911, 10203723467, 10203723902, 10203723468, 449471997, 10106987101, 449471999, 449472001, 10203723466, 449473090, 449472005, 449472007, 10102811254, 449472009, 10102811253, 449472010, 10203723638, 449472012, 10203723787, 10203723788, 10203723858, 10203723869, 449472636], "tags": {"highway": "unclassified"}}, {"type": "way", "id": 38170564, "nodes": [449473088, 449473451, 10203723711, 10203723525, 10203723526, 10203723527, 10203723503, 449472899, 10203723501, 10203723499, 10203723464, 10203723465, 449473563, 449473090], "tags": {"highway": "unclassified"}}, {"type": "way", "id": 47221339, "nodes": [796108844, 2141616520, 796108848, 796108855, 2141616476, 2142060310, 8269969202, 601704002, 601704008, 601704011, 601704014, 601704017, 601704028, 601704031, 601704037, 601704040, 2690921890, 601704043, 601704046, 2690921895, 601637084, 601637173, 601637174, 601637175, 601637176, 601637179, 601637180, 601637094], "tags": {"bicycle": "no", "expressway": "yes", "foot": "no", "highway": "trunk", "lanes": "4", "maxspeed": "80", "name": "\uc62c\ub9bc\ud53d\ub300\ub85c", "name:en": "Olympic-daero", "name:ja": "\u30aa\u30ea\u30f3\u30d4\u30c3\u30af\u5927\u8def", "name:ko": "\uc62c\ub9bc\ud53d\ub300\ub85c", "name:ko-Latn": "Ollimpikdaero", "ncat": "\uad6d\ub3c4", "oneway": "yes", "ref": "88", "source": "NTIC", "surface": "asphalt"}}, {"type": "way", "id": 65371811, "nodes": [798566739, 798566740, 798566741, 798566742, 3031379400, 798566744, 798566745], "tags": {"bicycle": "no", "highway": "trunk_link", "oneway": "yes"}}, {"type": "way", "id": 65371974, "nodes": [2456433663, 11582230930, 10705895889, 11582230957, 8459523597, 11582230927, 12627978069, 12627978063, 12627978070, 12627978071, 11582230924, 798568109, 798568110, 798568111, 7980080033, 798568085, 798568112, 8459541267, 11582230904, 798567737, 11582230905, 4605038146, 11582230906, 8456622827, 798567738, 11582230907, 8456619716, 11582230908, 4605038144, 4605038131], "tags": {"highway": "residential", "name": "\uc591\ucc9c\ub85c67\uae38", "name:en": "Yangcheon-ro 67-gil", "name:ko": "\uc591\ucc9c\ub85c67\uae38"}}, {"type": "way", "id": 65372034, "nodes": [436693466, 11582230951, 11582230949, 2825869583, 10681256710, 2825869606, 2825869605, 4605033164, 10681256655, 2825869578, 2825869597, 8457933628, 2825869586, 2825869588, 2825869596, 2825869594, 2825869585, 2825869599, 2825869592, 2825869582, 2825869584, 8457933641, 2825869598, 2825869600, 8434002967, 2825869603, 2825869595, 11582230926, 2825869604, 11582246026, 798568104], "tags": {"highway": "residential", "name": "\uc591\ucc9c\ub85c63\uae38", "name:en": "Yangcheon-ro 63-gil", "name:ko": "\uc591\ucc9c\ub85c63\uae38"}}, {"type": "way", "id": 97936992, "nodes": [1133534473, 1133534461], "tags": {"bicycle": "no", "highway": "trunk_link", "ncat": "\uad11\uc5ed\uc2dc\ub3c4\ub85c", "oneway": "yes", "review": "no", "source": "NTIC"}}, {"type": "way", "id": 97936993, "nodes": [436830207, 1133534456, 8456521433, 3414087347, 1133534459, 1133534469, 1133534471], "tags": {"highway": "trunk_link", "oneway": "yes"}}, {"type": "way", "id": 97936999, "nodes": [1133534459, 1133534466, 1133534463, 1133534480, 1133534447, 1133534460], "tags": {"highway": "trunk_link", "oneway": "yes"}}, {"type": "way", "id": 204144674, "nodes": [2141596008, 2141596039], "tags": {"highway": "trunk_link", "oneway": "yes"}}, {"type": "way", "id": 204144676, "nodes": [2938354331, 4696904534, 6706474635, 2141596090, 2141596057, 4696904532, 2141595962, 4696904531, 2141595987, 2141595950, 2141596008], "tags": {"bridge": "yes", "highway": "trunk_link", "layer": "2", "oneway": "yes"}}, {"type": "way", "id": 204144684, "nodes": [2141596006, 4695045506, 4695045503, 2141596091, 2141596049, 2141595940, 2141596045, 2141595929, 4695045517], "tags": {"highway": "trunk_link", "oneway": "yes"}}, {"type": "way", "id": 204144686, "nodes": [2141596076, 2141596018, 2141595982, 2141596051, 2141595960, 2141596083, 2141595958, 2141596088, 2141596063, 2141596037, 2141596013, 2141596041, 4695045515], "tags": {"bridge": "yes", "highway": "trunk_link", "layer": "1", "oneway": "yes"}}, {"type": "way", "id": 204144687, "nodes": [2141595962, 4696904533, 2141595943, 2141596044, 4695045510, 2141595999, 2141596043, 2141596062, 4695045509, 2141596036, 4695045508, 2141596032, 4695045507, 4695045513], "tags": {"bridge": "yes", "highway": "trunk_link", "layer": "2", "oneway": "yes"}}, {"type": "way", "id": 204146809, "nodes": [2141616520, 3031379406, 2141616462, 2141616440, 2141616542, 2141616508, 2141616509], "tags": {"highway": "trunk_link", "oneway": "yes"}}, {"type": "way", "id": 204146815, "nodes": [2141616456, 6706474614, 4694620271, 2141616466, 4694620272, 2141616461, 2141616430, 3031379411, 3031379413, 4694620273, 4694620274, 2141616428, 2141616519, 2141616497, 4694620275, 2141616498, 3031379410, 2141616465, 3031379405, 2141616514], "tags": {"highway": "trunk_link", "oneway": "yes"}}, {"type": "way", "id": 204146818, "nodes": [2141616462, 3031379407, 4694620254, 4694620256], "tags": {"highway": "trunk_link", "oneway": "yes"}}, {"type": "way", "id": 204146820, "nodes": [2141616546, 2141616545, 8537264169, 2141616489, 11821418277, 2142722963, 5983520754, 5983520751, 5983520748, 8537264184, 5983520745, 2141616414, 8455940603, 2141616482, 8455940602, 2141616492], "tags": {"bicycle": "yes", "foot": "yes", "highway": "residential", "name": "\ud5c8\uc900\ub85c", "name:en": "Heojun-ro", "name:ko": "\ud5c8\uc900\ub85c"}}, {"type": "way", "id": 204146822, "nodes": [2141616539, 3031379404, 2141616538, 2141616494, 2141616540, 2141616507, 11821418314, 7160386054, 3031379402, 2141616464, 3031379401, 436873141], "tags": {"highway": "trunk_link", "oneway": "yes"}}, {"type": "way", "id": 204146970, "nodes": [2141616415, 4694620278, 2141616517, 2141616510, 4694620277, 2141616445, 4694620276, 3031379409, 2141616465], "tags": {"highway": "trunk_link", "oneway": "yes"}}, {"type": "way", "id": 204261528, "nodes": [2142722910, 11821418309, 5983520736, 8455940609, 2142722963], "tags": {"highway": "residential"}}, {"type": "way", "id": 278164711, "nodes": [798568114, 11582230947, 2825869590, 11582245944, 11582245945, 2825869580, 11582245947, 11582230925, 798568104, 7617101084, 7617101083, 12627978065, 12627978063], "tags": {"highway": "residential", "name": "\uc591\ucc9c\ub85c65\uae38", "name:en": "Yangcheon-ro 65-gil", "name:ko": "\uc591\ucc9c\ub85c65\uae38"}}, {"type": "way", "id": 278164714, "nodes": [436873141, 11582245876, 2825869589, 11582245877, 2825869601, 10681256656, 2825869593, 2825869581, 2825869587, 2825869597], "tags": {"highway": "residential", "name": "\uc591\ucc9c\ub85c63\uae38", "name:en": "Yangcheon-ro 63-gil", "name:ko": "\uc591\ucc9c\ub85c63\uae38"}}, {"type": "way", "id": 299177416, "nodes": [798566628, 798566629, 798566745, 798566630, 798566631, 798566632, 798566633, 796108844], "tags": {"bicycle": "no", "expressway": "yes", "highway": "trunk", "lanes": "4", "maxspeed": "80", "name": "\uc62c\ub9bc\ud53d\ub300\ub85c", "name:en": "Olympic-daero", "name:ja": "\u30aa\u30ea\u30f3\u30d4\u30c3\u30af\u5927\u8def", "name:ko": "\uc62c\ub9bc\ud53d\ub300\ub85c", "name:ko-Latn": "Ollimpikdaero", "oneway": "yes", "ref": "88", "source": "NTIC"}}, {"type": "way", "id": 334293517, "nodes": [3347412393, 4681969841, 8456521435, 3414087349, 3414087352, 3414087369, 3414087375, 3414087382, 3414087387, 3414087798, 3414087812, 3414087859, 3414087861, 3414087860, 3414087857, 3414087855, 3414087854, 3414087851, 3414087848, 3414087837], "tags": {"highway": "unclassified", "name": "\ub178\uc744\uae38", "source": "survey, Bing"}}, {"type": "way", "id": 465528841, "nodes": [4871097568, 8738613140, 601637062, 601637164, 601637165, 601637166, 601637167, 601637168, 601637083, 601637169, 5842903328, 601703936, 601703942, 601703944, 601703820, 601703948, 7122163081, 601703957, 601703959, 601703965, 601703968, 601703970, 2142060299, 2142060300, 796110768, 2141616459, 2141616514, 796110778, 2141616539, 436764036, 436764035, 3031379403, 436764033, 436764032, 798566746], "tags": {"bicycle": "no", "expressway": "yes", "foot": "no", "highway": "trunk", "lanes": "4", "maxspeed": "80", "name": "\uc62c\ub9bc\ud53d\ub300\ub85c", "name:en": "Olympic-daero", "name:ja": "\u30aa\u30ea\u30f3\u30d4\u30c3\u30af\u5927\u8def", "name:ko": "\uc62c\ub9bc\ud53d\ub300\ub85c", "name:ko-Latn": "Ollimpikdaero", "oneway": "yes", "ref": "88", "source": "NTIC", "surface": "asphalt"}}, {"type": "way", "id": 465545551, "nodes": [4605022120, 11582245893, 3042645657, 436873140, 436873141], "tags": {"highway": "secondary", "name": "\uc591\ucc9c\ub85c61\uae38", "name:en": "Yangcheon-ro 61-gil", "name:ko": "\uc591\ucc9c\ub85c61\uae38", "ncat": "\uad11\uc5ed\uc2dc\ub3c4\ub85c", "review": "no", "source": "NTIC"}}, {"type": "way", "id": 465545607, "nodes": [4605024545, 8453295815, 11582245954, 3042645651], "tags": {"highway": "residential", "name": "\uc591\ucc9c\ub85c", "name:en": "Yangcheon-ro", "name:ko": "\uc591\ucc9c\ub85c"}}, {"type": "way", "id": 465546317, "nodes": [4605033164, 4605033165, 4605033166, 4605033167, 10681256709, 11582245875, 11582230954, 4605033168], "tags": {"highway": "residential", "name": "\uc591\ucc9c\ub85c", "name:en": "Yangcheon-ro", "name:ko": "\uc591\ucc9c\ub85c"}}, {"type": "way", "id": 465546898, "nodes": [4605038143, 798568087, 11582230910, 11582230909, 4605038144, 4605038145], "tags": {"highway": "residential", "name": "\uc591\ucc9c\ub85c67\uae38", "name:en": "Yangcheon-ro 67-gil", "name:ko": "\uc591\ucc9c\ub85c67\uae38", "religion": "christian"}}, {"type": "way", "id": 465546899, "nodes": [4605038146, 8436561097, 8436561094, 4605038147, 4605038148, 4605038149, 4605038150, 4605038151], "tags": {"highway": "residential", "name": "\uc591\ucc9c\ub85c67\uae38", "name:en": "Yangcheon-ro 67-gil", "name:ko": "\uc591\ucc9c\ub85c67\uae38"}}, {"type": "way", "id": 469635597, "nodes": [4639333447, 4656832325, 10669942889, 4656832307, 4656832326, 4656832311, 4639333448], "tags": {"highway": "residential"}}, {"type": "way", "id": 469635598, "nodes": [4639333449, 4605024545], "tags": {"highway": "residential"}}, {"type": "way", "id": 469635599, "nodes": [4639333447, 4639333450], "tags": {"highway": "residential"}}, {"type": "way", "id": 475040727, "nodes": [3414087837, 3414087833, 3414087827, 3414087822, 3414087367], "tags": {"highway": "unclassified", "source": "survey, Bing"}}, {"type": "way", "id": 475739780, "nodes": [4694620256, 4694620253, 4694620255, 2141616486, 4694620257, 4694620258, 2141616418, 4694620259, 4694620260, 2141616444, 4694620261, 2141616475, 3031379422, 2141616532], "tags": {"bridge": "yes", "highway": "trunk_link", "layer": "2", "oneway": "yes"}}, {"type": "way", "id": 475739781, "nodes": [2141616535, 4694620268, 2141616526, 4694620267, 2141616525, 2141616496, 4694620266, 2141616495, 2141616522, 4694620265, 2141616424, 4694620264, 2141616423, 4694620263, 4694620262, 2141616422, 2141616484, 4694620270, 2141616488, 4694620269, 2141616516, 2141616451, 12147253736, 2141616479], "tags": {"bridge": "yes", "highway": "trunk_link", "layer": "1", "oneway": "yes"}}, {"type": "way", "id": 475807873, "nodes": [4695045537, 2141596068, 2141596020, 2141596089, 2141596076], "tags": {"highway": "trunk_link", "oneway": "yes"}}, {"type": "way", "id": 475807875, "nodes": [4695045538, 2141595986, 2141596028, 2141596014, 2141596015, 2141596010, 2141595945, 6706464983, 2938354331], "tags": {"bicycle": "no", "bridge": "yes", "highway": "trunk_link", "layer": "2", "oneway": "yes"}}, {"type": "way", "id": 481043643, "nodes": [4739847042, 2141596080, 2141596039, 930164455, 5294398232, 5703055020, 2164945429, 5703054996, 930164469, 2858504972, 5703054986, 930164457, 5370459333, 4684562301, 4684562294, 4684562299, 4684562293, 653186424, 4684562292, 653191660, 4684562310, 798572250, 2139867172], "tags": {"bicycle": "no", "expressway": "yes", "foot": "no", "highway": "trunk", "horse": "no", "lanes": "5", "maxspeed": "80", "motor_vehicle": "yes", "name": "\uac15\ubcc0\ubd81\ub85c", "name:en": "Gangbyeonbuk-ro", "name:ko": "\uac15\ubcc0\ubd81\ub85c", "oneway": "yes", "ref": "23;77;70", "source": "NTIC", "toll": "no"}}, {"type": "way", "id": 481312981, "nodes": [2141616543, 4681899725, 2141596054, 2938354331, 4739847045, 1115265948, 436809361], "tags": {"bridge": "yes", "highway": "secondary", "layer": "2", "name": "\uac00\uc591\ub300\ub85c", "name:en": "Gayang-daero", "name:ja": "\u52a0\u967d\u5927\u8def", "name:ko": "\uac00\uc591\ub300\ub85c", "name:ko-Latn": "Gayangdaero", "ncat": "\uad11\uc5ed\uc2dc\ub3c4\ub85c", "review": "yes", "source": "NTIC"}}, {"type": "way", "id": 517254624, "nodes": [414683310, 11582245972, 10814323683, 8154128188, 3042643176, 3042645651, 11582245957, 3042643876, 11582245892, 4605022120, 11582245883, 4605033168, 436693467, 436693466, 11582245871, 436693465, 798568114, 436693464, 8459523608, 436693463, 11582230933, 2456433663], "tags": {"highway": "secondary", "name": "\uc591\ucc9c\ub85c", "name:en": "Yangcheon-ro", "name:ko": "\uc591\ucc9c\ub85c", "oneway": "no"}}, {"type": "way", "id": 532458281, "nodes": [1133534461, 1133534471], "tags": {"bicycle": "no", "highway": "trunk_link", "oneway": "yes"}}, {"type": "way", "id": 532458282, "nodes": [1133534471, 1133534451], "tags": {"bicycle": "no", "highway": "trunk_link", "oneway": "yes"}}, {"type": "way", "id": 532458283, "nodes": [3849185769, 1133534448, 8458097648, 8458097653, 436830207], "tags": {"highway": "trunk_link", "ncat": "\uad11\uc5ed\uc2dc\ub3c4\ub85c", "oneway": "yes", "review": "no", "source": "NTIC"}}, {"type": "way", "id": 532458284, "nodes": [1133534451, 5294397120, 436760158, 2141596006, 2141596070, 4739847044], "tags": {"bicycle": "no", "expressway": "yes", "highway": "trunk", "lanes": "5", "name": "\uac15\ubcc0\ubd81\ub85c", "name:en": "Gangbyeonbuk-ro", "name:ko": "\uac15\ubcc0\ubd81\ub85c", "ncat": "\uc9c0\ubc29\ub3c4;\uad6d\ub3c4", "oneway": "yes", "ref": "23;77;70", "review": "no", "source": "NTIC"}}, {"type": "way", "id": 532458285, "nodes": [1133534473, 436760157, 1133534451], "tags": {"bicycle": "no", "expressway": "yes", "foot": "no", "highway": "trunk", "horse": "no", "lanes": "5", "name": "\uac15\ubcc0\ubd81\ub85c", "name:en": "Gangbyeonbuk-ro", "name:ko": "\uac15\ubcc0\ubd81\ub85c", "ncat": "\uc9c0\ubc29\ub3c4;\uad6d\ub3c4", "oneway": "yes", "ref": "23;77;70", "review": "no", "source": "NTIC"}}, {"type": "way", "id": 547990908, "nodes": [5294397120, 5294398221, 5294398222, 5294398223, 5294398224], "tags": {"highway": "trunk_link", "oneway": "yes"}}, {"type": "way", "id": 547990911, "nodes": [5294398226, 5294398227, 5294398228, 5294398229, 5294398230, 5294398231, 5294398232], "tags": {"highway": "trunk_link", "oneway": "yes"}}, {"type": "way", "id": 547990912, "nodes": [5294398224, 5294398225, 5294398226], "tags": {"highway": "trunk_link", "layer": "-1", "oneway": "yes", "tunnel": "yes"}}, {"type": "way", "id": 599447356, "nodes": [5703054993, 5703054994, 5703054995, 5703054996], "tags": {"highway": "trunk_link", "oneway": "yes"}}, {"type": "way", "id": 599447359, "nodes": [5703055020, 5703055121, 5703055122], "tags": {"highway": "trunk_link", "oneway": "yes"}}, {"type": "way", "id": 910872323, "nodes": [1133534456, 8458097652, 8458097651, 8458097650, 8458097649, 8458097648], "tags": {"highway": "trunk_link"}}, {"type": "way", "id": 1275220101, "nodes": [3414087367, 3638110426, 12823414076], "tags": {"highway": "unclassified", "source": "survey, Bing"}}, {"type": "way", "id": 1385068798, "nodes": [12823414076, 3643726804, 3414087347, 3849185769], "tags": {"highway": "unclassified", "source": "survey, Bing"}}, {"type": "way", "id": 1385068799, "nodes": [1133534461, 1133534460, 3849185769], "tags": {"highway": "trunk_link", "ncat": "\uad11\uc5ed\uc2dc\ub3c4\ub85c", "oneway": "yes", "review": "no", "source": "NTIC"}}]}